Workbook

Sheet Setup
A1: ⚙️ SETUP — Accounts, Cards & Reference Lists
A3: 💰 INCOME SOURCES | D3: 💳 CREDIT CARDS
A4: Account / Source Name | B4: Monthly Amount (₹) | D4: Card Name | E4: Credit Limit (₹) | F4: Opening Dues (₹)
A5: Salary
A11: 🏦 SAVINGS ACCOUNTS | D11: 📋 CATEGORY → SUB-CATEGORY REFERENCE
A12: Account Name | B12: Opening Balance (₹) | D12: Category | F12: Sub-Categories
D13: Fixed Bills | F13: Rent / Home Loan EMI / Electricity / Internet / WiFi / Mobile Recharge / OTT Subscriptions / Insurance Premium / Gym / Fitness / Other Bill
D14: Food & Dining | F14: Restaurants / Swiggy / Zomato / Cafes / Street Food / Other
D15: Transport & Fuel | F15: Fuel / Auto / Cab / Metro / Bus / Parking / Vehicle Maintenance / Other
D16: Shopping & Clothing | F16: Clothing / Electronics / Home & Decor / Online Shopping / Other
D17: Entertainment & OTT | F17: Movies / Events / OTT Subscriptions / Gaming / Other
D18: Groceries | F18: Vegetables & Fruits / Dairy / Supermarket / Kirana Store / Other
D19: Investment | F19: SIP / Mutual Funds / Fixed Deposit / Gold / Others / Stocks / PPF / NPS / Other Investment
D20: Added to Savings | F20: (your savings account names)
D21: Credit Card Payment | F21: Full Payment / Minimum Due / Partial Payment
D22: Miscellaneous | F22: Medical / Education / Gifts / Charity / Other

Sheet Income
A1: 💰 INCOME TRACKER — Enter salary once in Setup; log extra income per month here
A3: Month | B3: Salary (₹) | C3: Extra Income (₹) | D3: Notes | E3: Total Income (₹)
A4: April | B4: =Setup!B5 | E4: =B4+C4
A5: May | B5: =Setup!B5 | E5: =B5+C5
A6: June | B6: =Setup!B5 | E6: =B6+C6
A7: July | B7: =Setup!B5 | E7: =B7+C7
A8: August | B8: =Setup!B5 | E8: =B8+C8
A9: September | B9: =Setup!B5 | E9: =B9+C9
A10: October | B10: =Setup!B5 | E10: =B10+C10
A11: November | B11: =Setup!B5 | E11: =B11+C11
A12: December | B12: =Setup!B5 | E12: =B12+C12
A13: January | B13: =Setup!B5 | E13: =B13+C13
A14: February | B14: =Setup!B5 | E14: =B14+C14
A15: March | B15: =Setup!B5 | E15: =B15+C15
A16: ANNUAL TOTAL | B16: =SUM(B4:B15) | C16: =SUM(C4:C15) | E16: =SUM(E4:E15)

Sheet April
A1: 📝 APRIL — EXPENSE LOG
A2: ℹ️ Date is DateTime. Category dropdown → Sub-category changes automatically. 'Added to Savings' → pick your saving account in Sub-category. CC spend → pick card in 'CC Name'. CC payment → increases card limit.
A4: # | B4: Date & Time | C4: Description | D4: Category | E4: Sub-category | F4: Amount (₹) | G4: Paid From | H4: CC Name | I4: Account | J4: Notes | L4: 📊 April Summary | M4: Amount (₹)
A5: =IF(F5<>"",ROW()-4,"") | L5: Total Expenses | M5: =F256
A6: =IF(F6<>"",ROW()-4,"") | L6: Income This Month | M6: =Income!E4
A7: =IF(F7<>"",ROW()-4,"") | L7: Net This Month | M7: =M6-M5
A8: =IF(F8<>"",ROW()-4,"") | L8: Savings 1 (this month) | M8: =IF(Setup!A13<>"",SUMIFS(F5:F255,D5:D255,"Added to Savings",I5:I255,Setup!A13)-SUMIFS(F5:F255,G5:G255,Setup!A13),"")
A9: =IF(F9<>"",ROW()-4,"") | L9: Savings 1 (balance) | M9: =IF(Setup!A13<>"",Setup!B13+(SUMIFS('April'!F5:F64,'April'!D5:D64,"Added to Savings",'April'!I5:I64,Setup!A13))-(SUMIFS('April'!F5:F64,'April'!G5:G64,Setup!A13)),"")
A10: =IF(F10<>"",ROW()-4,"") | L10: Savings 2 (this month) | M10: =IF(Setup!A14<>"",SUMIFS(F5:F255,D5:D255,"Added to Savings",I5:I255,Setup!A14)-SUMIFS(F5:F255,G5:G255,Setup!A14),"")
A11: =IF(F11<>"",ROW()-4,"") | L11: Savings 2 (balance) | M11: =IF(Setup!A14<>"",Setup!B14+(SUMIFS('April'!F5:F64,'April'!D5:D64,"Added to Savings",'April'!I5:I64,Setup!A14))-(SUMIFS('April'!F5:F64,'April'!G5:G64,Setup!A14)),"")
A12: =IF(F12<>"",ROW()-4,"") | L12: Savings 3 (this month) | M12: =IF(Setup!A15<>"",SUMIFS(F5:F255,D5:D255,"Added to Savings",I5:I255,Setup!A15)-SUMIFS(F5:F255,G5:G255,Setup!A15),"")
A13: =IF(F13<>"",ROW()-4,"") | L13: Savings 3 (balance) | M13: =IF(Setup!A15<>"",Setup!B15+(SUMIFS('April'!F5:F64,'April'!D5:D64,"Added to Savings",'April'!I5:I64,Setup!A15))-(SUMIFS('April'!F5:F64,'April'!G5:G64,Setup!A15)),"")
A14: =IF(F14<>"",ROW()-4,"") | L14: Savings 4 (this month) | M14: =IF(Setup!A16<>"",SUMIFS(F5:F255,D5:D255,"Added to Savings",I5:I255,Setup!A16)-SUMIFS(F5:F255,G5:G255,Setup!A16),"")
A15: =IF(F15<>"",ROW()-4,"") | L15: Savings 4 (balance) | M15: =IF(Setup!A16<>"",Setup!B16+(SUMIFS('April'!F5:F64,'April'!D5:D64,"Added to Savings",'April'!I5:I64,Setup!A16))-(SUMIFS('April'!F5:F64,'April'!G5:G64,Setup!A16)),"")
A16: =IF(F16<>"",ROW()-4,"") | L16: Savings 5 (this month) | M16: =IF(Setup!A17<>"",SUMIFS(F5:F255,D5:D255,"Added to Savings",I5:I255,Setup!A17)-SUMIFS(F5:F255,G5:G255,Setup!A17),"")
A17: =IF(F17<>"",ROW()-4,"") | L17: Savings 5 (balance) | M17: =IF(Setup!A17<>"",Setup!B17+(SUMIFS('April'!F5:F64,'April'!D5:D64,"Added to Savings",'April'!I5:I64,Setup!A17))-(SUMIFS('April'!F5:F64,'April'!G5:G64,Setup!A17)),"")
A18: =IF(F18<>"",ROW()-4,"") | L18: Fixed Bills Paid | M18: =SUMIF(D5:D255,"Fixed Bills",F5:F255)
A19: =IF(F19<>"",ROW()-4,"") | L19: Food & Dining | M19: =SUMIF(D5:D255,"Food & Dining",F5:F255)
A20: =IF(F20<>"",ROW()-4,"") | L20: Transport | M20: =SUMIF(D5:D255,"Transport & Fuel",F5:F255)
A21: =IF(F21<>"",ROW()-4,"") | L21: Groceries | M21: =SUMIF(D5:D255,"Groceries",F5:F255)
A22: =IF(F22<>"",ROW()-4,"") | L22: Shopping | M22: =SUMIF(D5:D255,"Shopping & Clothing",F5:F255)
A23: =IF(F23<>"",ROW()-4,"") | L23: Entertainment | M23: =SUMIF(D5:D255,"Entertainment & OTT",F5:F255)
A24: =IF(F24<>"",ROW()-4,"") | L24: Investment | M24: =SUMIF(D5:D255,"Investment",F5:F255)
A25: =IF(F25<>"",ROW()-4,"") | L25: Added to Savings | M25: =SUMIF(D5:D255,"Added to Savings",F5:F255)
A26: =IF(F26<>"",ROW()-4,"") | L26: CC Payments | M26: =SUMIF(D5:D255,"Credit Card Payment",F5:F255)
A27: =IF(F27<>"",ROW()-4,"") | L27: Miscellaneous | M27: =SUMIF(D5:D255,"Miscellaneous",F5:F255)
A28: =IF(F28<>"",ROW()-4,"")
A29: =IF(F29<>"",ROW()-4,"")
A30: =IF(F30<>"",ROW()-4,"")
A31: =IF(F31<>"",ROW()-4,"")
A32: =IF(F32<>"",ROW()-4,"")
A33: =IF(F33<>"",ROW()-4,"")
A34: =IF(F34<>"",ROW()-4,"")
A35: =IF(F35<>"",ROW()-4,"")
A36: =IF(F36<>"",ROW()-4,"")
A37: =IF(F37<>"",ROW()-4,"")
A38: =IF(F38<>"",ROW()-4,"")
A39: =IF(F39<>"",ROW()-4,"")
... A255: =IF(F255<>"",ROW()-4,"")
A256: TOTAL EXPENSES THIS MONTH | F256: =SUM(F5:F255)

Sheet May
A1: 📝 MAY — EXPENSE LOG
A2: ℹ️ Date is DateTime. Category dropdown → Sub-category changes automatically. 'Added to Savings' → pick your saving account in Sub-category. CC spend → pick card in 'CC Name'. CC payment → increases card limit.
A4: # | B4: Date & Time | C4: Description | D4: Category | E4: Sub-category | F4: Amount (₹) | G4: Paid From | H4: CC Name | I4: Account | J4: Notes | L4: 📊 May Summary | M4: Amount (₹)
A5: =IF(F5<>"",ROW()-4,"") | L5: Total Expenses | M5: =F256
A6: =IF(F6<>"",ROW()-4,"") | L6: Income This Month | M6: =Income!E5
A7: =IF(F7<>"",ROW()-4,"") | L7: Net This Month | M7: =M6-M5
A8: =IF(F8<>"",ROW()-4,"") | L8: Savings 1 (this month) | M8: =IF(Setup!A13<>"",SUMIFS(F5:F255,D5:D255,"Added to Savings",I5:I255,Setup!A13)-SUMIFS(F5:F255,G5:G255,Setup!A13),"")
A9: =IF(F9<>"",ROW()-4,"") | L9: Savings 1 (balance) | M9: =IF(Setup!A13<>"",Setup!B13+(SUMIFS('April'!F5:F64,'April'!D5:D64,"Added to Savings",'April'!I5:I64,Setup!A13)+SUMIFS('May'!F5:F64,'May'!D5:D64,"Added to Savings",'May'!I5:I64,Setup!A13))-(SUMIFS('April'!F5:F64,'April'!G5:G64,Setup!A13)+SUMIFS('May'!F5:F64,'May'!G5:G64,Setup!A13)),"")
A10: =IF(F10<>"",ROW()-4,"") | L10: Savings 2 (this month) | M10: =IF(Setup!A14<>"",SUMIFS(F5:F255,D5:D255,"Added to Savings",I5:I255,Setup!A14)-SUMIFS(F5:F255,G5:G255,Setup!A14),"")
A11: =IF(F11<>"",ROW()-4,"") | L11: Savings 2 (balance) | M11: =IF(Setup!A14<>"",Setup!B14+(SUMIFS('April'!F5:F64,'April'!D5:D64,"Added to Savings",'April'!I5:I64,Setup!A14)+SUMIFS('May'!F5:F64,'May'!D5:D64,"Added to Savings",'May'!I5:I64,Setup!A14))-(SUMIFS('April'!F5:F64,'April'!G5:G64,Setup!A14)+SUMIFS('May'!F5:F64,'May'!G5:G64,Setup!A14)),"")
A12: =IF(F12<>"",ROW()-4,"") | L12: Savings 3 (this month) | M12: =IF(Setup!A15<>"",SUMIFS(F5:F255,D5:D255,"Added to Savings",I5:I255,Setup!A15)-SUMIFS(F5:F255,G5:G255,Setup!A15),"")
A13: =IF(F13<>"",ROW()-4,"") | L13: Savings 3 (balance) | M13: =IF(Setup!A15<>"",Setup!B15+(SUMIFS('April'!F5:F64,'April'!D5:D64,"Added to Savings",'April'!I5:I64,Setup!A15)+SUMIFS('May'!F5:F64,'May'!D5:D64,"Added to Savings",'May'!I5:I64,Setup!A15))-(SUMIFS('April'!F5:F64,'April'!G5:G64,Setup!A15)+SUMIFS('May'!F5:F64,'May'!G5:G64,Setup!A15)),"")
A14: =IF(F14<>"",ROW()-4,"") | L14: Savings 4 (this month) | M14: =IF(Setup!A16<>"",SUMIFS(F5:F255,D5:D255,"Added to Savings",I5:I255,Setup!A16)-SUMIFS(F5:F255,G5:G255,Setup!A16),"")
A15: =IF(F15<>"",ROW()-4,"") | L15: Savings 4 (balance) | M15: =IF(Setup!A16<>"",Setup!B16+(SUMIFS('April'!F5:F64,'April'!D5:D64,"Added to Savings",'April'!I5:I64,Setup!A16)+SUMIFS('May'!F5:F64,'May'!D5:D64,"Added to Savings",'May'!I5:I64,Setup!A16))-(SUMIFS('April'!F5:F64,'April'!G5:G64,Setup!A16)+SUMIFS('May'!F5:F64,'May'!G5:G64,Setup!A16)),"")
A16: =IF(F16<>"",ROW()-4,"") | L16: Savings 5 (this month) | M16: =IF(Setup!A17<>"",SUMIFS(F5:F255,D5:D255,"Added to Savings",I5:I255,Setup!A17)-SUMIFS(F5:F255,G5:G255,Setup!A17),"")
A17: =IF(F17<>"",ROW()-4,"") | L17: Savings 5 (balance) | M17: =IF(Setup!A17<>"",Setup!B17+(SUMIFS('April'!F5:F64,'April'!D5:D64,"Added to Savings",'April'!I5:I64,Setup!A17)+SUMIFS('May'!F5:F64,'May'!D5:D64,"Added to Savings",'May'!I5:I64,Setup!A17))-(SUMIFS('April'!F5:F64,'April'!G5:G64,Setup!A17)+SUMIFS('May'!F5:F64,'May'!G5:G64,Setup!A17)),"")
A18: =IF(F18<>"",ROW()-4,"") | L18: Fixed Bills Paid | M18: =SUMIF(D5:D255,"Fixed Bills",F5:F255)
A19: =IF(F19<>"",ROW()-4,"") | L19: Food & Dining | M19: =SUMIF(D5:D255,"Food & Dining",F5:F255)
A20: =IF(F20<>"",ROW()-4,"") | L20: Transport | M20: =SUMIF(D5:D255,"Transport & Fuel",F5:F255)
A21: =IF(F21<>"",ROW()-4,"") | L21: Groceries | M21: =SUMIF(D5:D255,"Groceries",F5:F255)
A22: =IF(F22<>"",ROW()-4,"") | L22: Shopping | M22: =SUMIF(D5:D255,"Shopping & Clothing",F5:F255)
A23: =IF(F23<>"",ROW()-4,"") | L23: Entertainment | M23: =SUMIF(D5:D255,"Entertainment & OTT",F5:F255)
A24: =IF(F24<>"",ROW()-4,"") | L24: Investment | M24: =SUMIF(D5:D255,"Investment",F5:F255)
A25: =IF(F25<>"",ROW()-4,"") | L25: Added to Savings | M25: =SUMIF(D5:D255,"Added to Savings",F5:F255)
A26: =IF(F26<>"",ROW()-4,"") | L26: CC Payments | M26: =SUMIF(D5:D255,"Credit Card Payment",F5:F255)
A27: =IF(F27<>"",ROW()-4,"") | L27: Miscellaneous | M27: =SUMIF(D5:D255,"Miscellaneous",F5:F255)
A28: =IF(F28<>"",ROW()-4,"")
A29: =IF(F29<>"",ROW()-4,"")
A30: =IF(F30<>"",ROW()-4,"")
A31: =IF(F31<>"",ROW()-4,"")
A32: =IF(F32<>"",ROW()-4,"")
A33: =IF(F33<>"",ROW()-4,"")
A34: =IF(F34<>"",ROW()-4,"")
A35: =IF(F35<>"",ROW()-4,"")
A36: =IF(F36<>"",ROW()-4,"")
A37: =IF(F37<>"",ROW()-4,"")
A38: =IF(F38<>"",ROW()-4,"")
A39: =IF(F39<>"",ROW()-4,"")
... A255: =IF(F255<>"",ROW()-4,"")
A256: TOTAL EXPENSES THIS MONTH | F256: =SUM(F5:F255)

Sheet June
A1: 📝 JUNE — EXPENSE LOG
A2: ℹ️ Date is DateTime. Category dropdown → Sub-category changes automatically. 'Added to Savings' → pick your saving account in Sub-category. CC spend → pick card in 'CC Name'. CC payment → increases card limit.
A4: # | B4: Date & Time | C4: Description | D4: Category | E4: Sub-category | F4: Amount (₹) | G4: Paid From | H4: CC Name | I4: Account | J4: Notes | L4: 📊 June Summary | M4: Amount (₹)
A5: =IF(F5<>"",ROW()-4,"") | L5: Total Expenses | M5: =F256
A6: =IF(F6<>"",ROW()-4,"") | L6: Income This Month | M6: =Income!E6
A7: =IF(F7<>"",ROW()-4,"") | L7: Net This Month | M7: =M6-M5
A8: =IF(F8<>"",ROW()-4,"") | L8: Savings 1 (this month) | M8: =IF(Setup!A13<>"",SUMIFS(F5:F255,D5:D255,"Added to Savings",I5:I255,Setup!A13)-SUMIFS(F5:F255,G5:G255,Setup!A13),"")
A9: =IF(F9<>"",ROW()-4,"") | L9: Savings 1 (balance) | M9: =IF(Setup!A13<>"",Setup!B13+(SUMIFS('April'!F5:F64,'April'!D5:D64,"Added to Savings",'April'!I5:I64,Setup!A13)+SUMIFS('May'!F5:F64,'May'!D5:D64,"Added to Savings",'May'!I5:I64,Setup!A13)+SUMIFS('June'!F5:F64,'June'!D5:D64,"Added to Savings",'June'!I5:I64,Setup!A13))-(SUMIFS('April'!F5:F64,'April'!G5:G64,Setup!A13)+SUMIFS('May'!F5:F64,'May'!G5:G64,Setup!A13)+SUMIFS('June'!F5:F64,'June'!G5:G64,Setup!A13)),"")
A10: =IF(F10<>"",ROW()-4,"") | L10: Savings 2 (this month) | M10: =IF(Setup!A14<>"",SUMIFS(F5:F255,D5:D255,"Added to Savings",I5:I255,Setup!A14)-SUMIFS(F5:F255,G5:G255,Setup!A14),"")
A11: =IF(F11<>"",ROW()-4,"") | L11: Savings 2 (balance) | M11: =IF(Setup!A14<>"",Setup!B14+(SUMIFS('April'!F5:F64,'April'!D5:D64,"Added to Savings",'April'!I5:I64,Setup!A14)+SUMIFS('May'!F5:F64,'May'!D5:D64,"Added to Savings",'May'!I5:I64,Setup!A14)+SUMIFS('June'!F5:F64,'June'!D5:D64,"Added to Savings",'June'!I5:I64,Setup!A14))-(SUMIFS('April'!F5:F64,'April'!G5:G64,Setup!A14)+SUMIFS('May'!F5:F64,'May'!G5:G64,Setup!A14)+SUMIFS('June'!F5:F64,'June'!G5:G64,Setup!A14)),"")
A12: =IF(F12<>"",ROW()-4,"") | L12: Savings 3 (this month) | M12: =IF(Setup!A15<>"",SUMIFS(F5:F255,D5:D255,"Added to Savings",I5:I255,Setup!A15)-SUMIFS(F5:F255,G5:G255,Setup!A15),"")
A13: =IF(F13<>"",ROW()-4,"") | L13: Savings 3 (balance) | M13: =IF(Setup!A15<>"",Setup!B15+(SUMIFS('April'!F5:F64,'April'!D5:D64,"Added to Savings",'April'!I5:I64,Setup!A15)+SUMIFS('May'!F5:F64,'May'!D5:D64,"Added to Savings",'May'!I5:I64,Setup!A15)+SUMIFS('June'!F5:F64,'June'!D5:D64,"Added to Savings",'June'!I5:I64,Setup!A15))-(SUMIFS('April'!F5:F64,'April'!G5:G64,Setup!A15)+SUMIFS('May'!F5:F64,'May'!G5:G64,Setup!A15)+SUMIFS('June'!F5:F64,'June'!G5:G64,Setup!A15)),"")
A14: =IF(F14<>"",ROW()-4,"") | L14: Savings 4 (this month) | M14: =IF(Setup!A16<>"",SUMIFS(F5:F255,D5:D255,"Added to Savings",I5:I255,Setup!A16)-SUMIFS(F5:F255,G5:G255,Setup!A16),"")
A15: =IF(F15<>"",ROW()-4,"") | L15: Savings 4 (balance) | M15: =IF(Setup!A16<>"",Setup!B16+(SUMIFS('April'!F5:F64,'April'!D5:D64,"Added to Savings",'April'!I5:I64,Setup!A16)+SUMIFS('May'!F5:F64,'May'!D5:D64,"Added to Savings",'May'!I5:I64,Setup!A16)+SUMIFS('June'!F5:F64,'June'!D5:D64,"Added to Savings",'June'!I5:I64,Setup!A16))-(SUMIFS('April'!F5:F64,'April'!G5:G64,Setup!A16)+SUMIFS('May'!F5:F64,'May'!G5:G64,Setup!A16)+SUMIFS('June'!F5:F64,'June'!G5:G64,Setup!A16)),"")
A16: =IF(F16<>"",ROW()-4,"") | L16: Savings 5 (this month) | M16: =IF(Setup!A17<>"",SUMIFS(F5:F255,D5:D255,"Added to Savings",I5:I255,Setup!A17)-SUMIFS(F5:F255,G5:G255,Setup!A17),"")
A17: =IF(F17<>"",ROW()-4,"") | L17: Savings 5 (balance) | M17: =IF(Setup!A17<>"",Setup!B17+(SUMIFS('April'!F5:F64,'April'!D5:D64,"Added to Savings",'April'!I5:I64,Setup!A17)+SUMIFS('May'!F5:F64,'May'!D5:D64,"Added to Savings",'May'!I5:I64,Setup!A17)+SUMIFS('June'!F5:F64,'June'!D5:D64,"Added to Savings",'June'!I5:I64,Setup!A17))-(SUMIFS('April'!F5:F64,'April'!G5:G64,Setup!A17)+SUMIFS('May'!F5:F64,'May'!G5:G64,Setup!A17)+SUMIFS('June'!F5:F64,'June'!G5:G64,Setup!A17)),"")
A18: =IF(F18<>"",ROW()-4,"") | L18: Fixed Bills Paid | M18: =SUMIF(D5:D255,"Fixed Bills",F5:F255)
A19: =IF(F19<>"",ROW()-4,"") | L19: Food & Dining | M19: =SUMIF(D5:D255,"Food & Dining",F5:F255)
A20: =IF(F20<>"",ROW()-4,"") | L20: Transport | M20: =SUMIF(D5:D255,"Transport & Fuel",F5:F255)
A21: =IF(F21<>"",ROW()-4,"") | L21: Groceries | M21: =SUMIF(D5:D255,"Groceries",F5:F255)
A22: =IF(F22<>"",ROW()-4,"") | L22: Shopping | M22: =SUMIF(D5:D255,"Shopping & Clothing",F5:F255)
A23: =IF(F23<>"",ROW()-4,"") | L23: Entertainment | M23: =SUMIF(D5:D255,"Entertainment & OTT",F5:F255)
A24: =IF(F24<>"",ROW()-4,"") | L24: Investment | M24: =SUMIF(D5:D255,"Investment",F5:F255)
A25: =IF(F25<>"",ROW()-4,"") | L25: Added to Savings | M25: =SUMIF(D5:D255,"Added to Savings",F5:F255)
A26: =IF(F26<>"",ROW()-4,"") | L26: CC Payments | M26: =SUMIF(D5:D255,"Credit Card Payment",F5:F255)
A27: =IF(F27<>"",ROW()-4,"") | L27: Miscellaneous | M27: =SUMIF(D5:D255,"Miscellaneous",F5:F255)
A28: =IF(F28<>"",ROW()-4,"")
A29: =IF(F29<>"",ROW()-4,"")
A30: =IF(F30<>"",ROW()-4,"")
A31: =IF(F31<>"",ROW()-4,"")
A32: =IF(F32<>"",ROW()-4,"")
A33: =IF(F33<>"",ROW()-4,"")
A34: =IF(F34<>"",ROW()-4,"")
A35: =IF(F35<>"",ROW()-4,"")
A36: =IF(F36<>"",ROW()-4,"")
A37: =IF(F37<>"",ROW()-4,"")
A38: =IF(F38<>"",ROW()-4,"")
A39: =IF(F39<>"",ROW()-4,"")
... A255: =IF(F255<>"",ROW()-4,"")
A256: TOTAL EXPENSES THIS MONTH | F256: =SUM(F5:F255)

Sheet July
A1: 📝 JULY — EXPENSE LOG
A2: ℹ️ Date is DateTime. Category dropdown → Sub-category changes automatically. 'Added to Savings' → pick your saving account in Sub-category. CC spend → pick card in 'CC Name'. CC payment → increases card limit.
A4: # | B4: Date & Time | C4: Description | D4: Category | E4: Sub-category | F4: Amount (₹) | G4: Paid From | H4: CC Name | I4: Account | J4: Notes | L4: 📊 July Summary | M4: Amount (₹)
A5: =IF(F5<>"",ROW()-4,"") | L5: Total Expenses | M5: =F256
A6: =IF(F6<>"",ROW()-4,"") | L6: Income This Month | M6: =Income!E7
A7: =IF(F7<>"",ROW()-4,"") | L7: Net This Month | M7: =M6-M5
A8: =IF(F8<>"",ROW()-4,"") | L8: Savings 1 (this month) | M8: =IF(Setup!A13<>"",SUMIFS(F5:F255,D5:D255,"Added to Savings",I5:I255,Setup!A13)-SUMIFS(F5:F255,G5:G255,Setup!A13),"")
A9: =IF(F9<>"",ROW()-4,"") | L9: Savings 1 (balance) | M9: =IF(Setup!A13<>"",Setup!B13+(SUMIFS('April'!F5:F64,'April'!D5:D64,"Added to Savings",'April'!I5:I64,Setup!A13)+SUMIFS('May'!F5:F64,'May'!D5:D64,"Added to Savings",'May'!I5:I64,Setup!A13)+SUMIFS('June'!F5:F64,'June'!D5:D64,"Added to Savings",'June'!I5:I64,Setup!A13)+SUMIFS('July'!F5:F64,'July'!D5:D64,"Added to Savings",'July'!I5:I64,Setup!A13))-(SUMIFS('April'!F5:F64,'April'!G5:G64,Setup!A13)+SUMIFS('May'!F5:F64,'May'!G5:G64,Setup!A13)+SUMIFS('June'!F5:F64,'June'!G5:G64,Setup!A13)+SUMIFS('July'!F5:F64,'July'!G5:G64,Setup!A13)),"")
A10: =IF(F10<>"",ROW()-4,"") | L10: Savings 2 (this month) | M10: =IF(Setup!A14<>"",SUMIFS(F5:F255,D5:D255,"Added to Savings",I5:I255,Setup!A14)-SUMIFS(F5:F255,G5:G255,Setup!A14),"")
A11: =IF(F11<>"",ROW()-4,"") | L11: Savings 2 (balance) | M11: =IF(Setup!A14<>"",Setup!B14+(SUMIFS('April'!F5:F64,'April'!D5:D64,"Added to Savings",'April'!I5:I64,Setup!A14)+SUMIFS('May'!F5:F64,'May'!D5:D64,"Added to Savings",'May'!I5:I64,Setup!A14)+SUMIFS('June'!F5:F64,'June'!D5:D64,"Added to Savings",'June'!I5:I64,Setup!A14)+SUMIFS('July'!F5:F64,'July'!D5:D64,"Added to Savings",'July'!I5:I64,Setup!A14))-(SUMIFS('April'!F5:F64,'April'!G5:G64,Setup!A14)+SUMIFS('May'!F5:F64,'May'!G5:G64,Setup!A14)+SUMIFS('June'!F5:F64,'June'!G5:G64,Setup!A14)+SUMIFS('July'!F5:F64,'July'!G5:G64,Setup!A14)),"")
A12: =IF(F12<>"",ROW()-4,"") | L12: Savings 3 (this month) | M12: =IF(Setup!A15<>"",SUMIFS(F5:F255,D5:D255,"Added to Savings",I5:I255,Setup!A15)-SUMIFS(F5:F255,G5:G255,Setup!A15),"")
A13: =IF(F13<>"",ROW()-4,"") | L13: Savings 3 (balance) | M13: =IF(Setup!A15<>"",Setup!B15+(SUMIFS('April'!F5:F64,'April'!D5:D64,"Added to Savings",'April'!I5:I64,Setup!A15)+SUMIFS('May'!F5:F64,'May'!D5:D64,"Added to Savings",'May'!I5:I64,Setup!A15)+SUMIFS('June'!F5:F64,'June'!D5:D64,"Added to Savings",'June'!I5:I64,Setup!A15)+SUMIFS('July'!F5:F64,'July'!D5:D64,"Added to Savings",'July'!I5:I64,Setup!A15))-(SUMIFS('April'!F5:F64,'April'!G5:G64,Setup!A15)+SUMIFS('May'!F5:F64,'May'!G5:G64,Setup!A15)+SUMIFS('June'!F5:F64,'June'!G5:G64,Setup!A15)+SUMIFS('July'!F5:F64,'July'!G5:G64,Setup!A15)),"")
A14: =IF(F14<>"",ROW()-4,"") | L14: Savings 4 (this month) | M14: =IF(Setup!A16<>"",SUMIFS(F5:F255,D5:D255,"Added to Savings",I5:I255,Setup!A16)-SUMIFS(F5:F255,G5:G255,Setup!A16),"")
A15: =IF(F15<>"",ROW()-4,"") | L15: Savings 4 (balance) | M15: =IF(Setup!A16<>"",Setup!B16+(SUMIFS('April'!F5:F64,'April'!D5:D64,"Added to Savings",'April'!I5:I64,Setup!A16)+SUMIFS('May'!F5:F64,'May'!D5:D64,"Added to Savings",'May'!I5:I64,Setup!A16)+SUMIFS('June'!F5:F64,'June'!D5:D64,"Added to Savings",'June'!I5:I64,Setup!A16)+SUMIFS('July'!F5:F64,'July'!D5:D64,"Added to Savings",'July'!I5:I64,Setup!A16))-(SUMIFS('April'!F5:F64,'April'!G5:G64,Setup!A16)+SUMIFS('May'!F5:F64,'May'!G5:G64,Setup!A16)+SUMIFS('June'!F5:F64,'June'!G5:G64,Setup!A16)+SUMIFS('July'!F5:F64,'July'!G5:G64,Setup!A16)),"")
A16: =IF(F16<>"",ROW()-4,"") | L16: Savings 5 (this month) | M16: =IF(Setup!A17<>"",SUMIFS(F5:F255,D5:D255,"Added to Savings",I5:I255,Setup!A17)-SUMIFS(F5:F255,G5:G255,Setup!A17),"")
A17: =IF(F17<>"",ROW()-4,"") | L17: Savings 5 (balance) | M17: =IF(Setup!A17<>"",Setup!B17+(SUMIFS('April'!F5:F64,'April'!D5:D64,"Added to Savings",'April'!I5:I64,Setup!A17)+SUMIFS('May'!F5:F64,'May'!D5:D64,"Added to Savings",'May'!I5:I64,Setup!A17)+SUMIFS('June'!F5:F64,'June'!D5:D64,"Added to Savings",'June'!I5:I64,Setup!A17)+SUMIFS('July'!F5:F64,'July'!D5:D64,"Added to Savings",'July'!I5:I64,Setup!A17))-(SUMIFS('April'!F5:F64,'April'!G5:G64,Setup!A17)+SUMIFS('May'!F5:F64,'May'!G5:G64,Setup!A17)+SUMIFS('June'!F5:F64,'June'!G5:G64,Setup!A17)+SUMIFS('July'!F5:F64,'July'!G5:G64,Setup!A17)),"")
A18: =IF(F18<>"",ROW()-4,"") | L18: Fixed Bills Paid | M18: =SUMIF(D5:D255,"Fixed Bills",F5:F255)
A19: =IF(F19<>"",ROW()-4,"") | L19: Food & Dining | M19: =SUMIF(D5:D255,"Food & Dining",F5:F255)
A20: =IF(F20<>"",ROW()-4,"") | L20: Transport | M20: =SUMIF(D5:D255,"Transport & Fuel",F5:F255)
A21: =IF(F21<>"",ROW()-4,"") | L21: Groceries | M21: =SUMIF(D5:D255,"Groceries",F5:F255)
A22: =IF(F22<>"",ROW()-4,"") | L22: Shopping | M22: =SUMIF(D5:D255,"Shopping & Clothing",F5:F255)
A23: =IF(F23<>"",ROW()-4,"") | L23: Entertainment | M23: =SUMIF(D5:D255,"Entertainment & OTT",F5:F255)
A24: =IF(F24<>"",ROW()-4,"") | L24: Investment | M24: =SUMIF(D5:D255,"Investment",F5:F255)
A25: =IF(F25<>"",ROW()-4,"") | L25: Added to Savings | M25: =SUMIF(D5:D255,"Added to Savings",F5:F255)
A26: =IF(F26<>"",ROW()-4,"") | L26: CC Payments | M26: =SUMIF(D5:D255,"Credit Card Payment",F5:F255)
A27: =IF(F27<>"",ROW()-4,"") | L27: Miscellaneous | M27: =SUMIF(D5:D255,"Miscellaneous",F5:F255)
A28: =IF(F28<>"",ROW()-4,"")
A29: =IF(F29<>"",ROW()-4,"")
A30: =IF(F30<>"",ROW()-4,"")
A31: =IF(F31<>"",ROW()-4,"")
A32: =IF(F32<>"",ROW()-4,"")
A33: =IF(F33<>"",ROW()-4,"")
A34: =IF(F34<>"",ROW()-4,"")
A35: =IF(F35<>"",ROW()-4,"")
A36: =IF(F36<>"",ROW()-4,"")
A37: =IF(F37<>"",ROW()-4,"")
A38: =IF(F38<>"",ROW()-4,"")
A39: =IF(F39<>"",ROW()-4,"")
... A255: =IF(F255<>"",ROW()-4,"")
A256: TOTAL EXPENSES THIS MONTH | F256: =SUM(F5:F255)

Sheet August
A1: 📝 AUGUST — EXPENSE LOG
A2: ℹ️ Date is DateTime. Category dropdown → Sub-category changes automatically. 'Added to Savings' → pick your saving account in Sub-category. CC spend → pick card in 'CC Name'. CC payment → increases card limit.
A4: # | B4: Date & Time | C4: Description | D4: Category | E4: Sub-category | F4: Amount (₹) | G4: Paid From | H4: CC Name | I4: Account | J4: Notes | L4: 📊 August Summary | M4: Amount (₹)
A5: =IF(F5<>"",ROW()-4,"") | L5: Total Expenses | M5: =F256
A6: =IF(F6<>"",ROW()-4,"") | L6: Income This Month | M6: =Income!E8
A7: =IF(F7<>"",ROW()-4,"") | L7: Net This Month | M7: =M6-M5
A8: =IF(F8<>"",ROW()-4,"") | L8: Savings 1 (this month) | M8: =IF(Setup!A13<>"",SUMIFS(F5:F255,D5:D255,"Added to Savings",I5:I255,Setup!A13)-SUMIFS(F5:F255,G5:G255,Setup!A13),"")
A9: =IF(F9<>"",ROW()-4,"") | L9: Savings 1 (balance) | M9: =IF(Setup!A13<>"",Setup!B13+(SUMIFS('April'!F5:F64,'April'!D5:D64,"Added to Savings",'April'!I5:I64,Setup!A13)+SUMIFS('May'!F5:F64,'May'!D5:D64,"Added to Savings",'May'!I5:I64,Setup!A13)+SUMIFS('June'!F5:F64,'June'!D5:D64,"Added to Savings",'June'!I5:I64,Setup!A13)+SUMIFS('July'!F5:F64,'July'!D5:D64,"Added to Savings",'July'!I5:I64,Setup!A13)+SUMIFS('August'!F5:F64,'August'!D5:D64,"Added to Savings",'August'!I5:I64,Setup!A13))-(SUMIFS('April'!F5:F64,'April'!G5:G64,Setup!A13)+SUMIFS('May'!F5:F64,'May'!G5:G64,Setup!A13)+SUMIFS('June'!F5:F64,'June'!G5:G64,Setup!A13)+SUMIFS('July'!F5:F64,'July'!G5:G64,Setup!A13)+SUMIFS('August'!F5:F64,'August'!G5:G64,Setup!A13)),"")
A10: =IF(F10<>"",ROW()-4,"") | L10: Savings 2 (this month) | M10: =IF(Setup!A14<>"",SUMIFS(F5:F255,D5:D255,"Added to Savings",I5:I255,Setup!A14)-SUMIFS(F5:F255,G5:G255,Setup!A14),"")
A11: =IF(F11<>"",ROW()-4,"") | L11: Savings 2 (balance) | M11: =IF(Setup!A14<>"",Setup!B14+(SUMIFS('April'!F5:F64,'April'!D5:D64,"Added to Savings",'April'!I5:I64,Setup!A14)+SUMIFS('May'!F5:F64,'May'!D5:D64,"Added to Savings",'May'!I5:I64,Setup!A14)+SUMIFS('June'!F5:F64,'June'!D5:D64,"Added to Savings",'June'!I5:I64,Setup!A14)+SUMIFS('July'!F5:F64,'July'!D5:D64,"Added to Savings",'July'!I5:I64,Setup!A14)+SUMIFS('August'!F5:F64,'August'!D5:D64,"Added to Savings",'August'!I5:I64,Setup!A14))-(SUMIFS('April'!F5:F64,'April'!G5:G64,Setup!A14)+SUMIFS('May'!F5:F64,'May'!G5:G64,Setup!A14)+SUMIFS('June'!F5:F64,'June'!G5:G64,Setup!A14)+SUMIFS('July'!F5:F64,'July'!G5:G64,Setup!A14)+SUMIFS('August'!F5:F64,'August'!G5:G64,Setup!A14)),"")
A12: =IF(F12<>"",ROW()-4,"") | L12: Savings 3 (this month) | M12: =IF(Setup!A15<>"",SUMIFS(F5:F255,D5:D255,"Added to Savings",I5:I255,Setup!A15)-SUMIFS(F5:F255,G5:G255,Setup!A15),"")
A13: =IF(F13<>"",ROW()-4,"") | L13: Savings 3 (balance) | M13: =IF(Setup!A15<>"",Setup!B15+(SUMIFS('April'!F5:F64,'April'!D5:D64,"Added to Savings",'April'!I5:I64,Setup!A15)+SUMIFS('May'!F5:F64,'May'!D5:D64,"Added to Savings",'May'!I5:I64,Setup!A15)+SUMIFS('June'!F5:F64,'June'!D5:D64,"Added to Savings",'June'!I5:I64,Setup!A15)+SUMIFS('July'!F5:F64,'July'!D5:D64,"Added to Savings",'July'!I5:I64,Setup!A15)+SUMIFS('August'!F5:F64,'August'!D5:D64,"Added to Savings",'August'!I5:I64,Setup!A15))-(SUMIFS('April'!F5:F64,'April'!G5:G64,Setup!A15)+SUMIFS('May'!F5:F64,'May'!G5:G64,Setup!A15)+SUMIFS('June'!F5:F64,'June'!G5:G64,Setup!A15)+SUMIFS('July'!F5:F64,'July'!G5:G64,Setup!A15)+SUMIFS('August'!F5:F64,'August'!G5:G64,Setup!A15)),"")
A14: =IF(F14<>"",ROW()-4,"") | L14: Savings 4 (this month) | M14: =IF(Setup!A16<>"",SUMIFS(F5:F255,D5:D255,"Added to Savings",I5:I255,Setup!A16)-SUMIFS(F5:F255,G5:G255,Setup!A16),"")
A15: =IF(F15<>"",ROW()-4,"") | L15: Savings 4 (balance) | M15: =IF(Setup!A16<>"",Setup!B16+(SUMIFS('April'!F5:F64,'April'!D5:D64,"Added to Savings",'April'!I5:I64,Setup!A16)+SUMIFS('May'!F5:F64,'May'!D5:D64,"Added to Savings",'May'!I5:I64,Setup!A16)+SUMIFS('June'!F5:F64,'June'!D5:D64,"Added to Savings",'June'!I5:I64,Setup!A16)+SUMIFS('July'!F5:F64,'July'!D5:D64,"Added to Savings",'July'!I5:I64,Setup!A16)+SUMIFS('August'!F5:F64,'August'!D5:D64,"Added to Savings",'August'!I5:I64,Setup!A16))-(SUMIFS('April'!F5:F64,'April'!G5:G64,Setup!A16)+SUMIFS('May'!F5:F64,'May'!G5:G64,Setup!A16)+SUMIFS('June'!F5:F64,'June'!G5:G64,Setup!A16)+SUMIFS('July'!F5:F64,'July'!G5:G64,Setup!A16)+SUMIFS('August'!F5:F64,'August'!G5:G64,Setup!A16)),"")
A16: =IF(F16<>"",ROW()-4,"") | L16: Savings 5 (this month) | M16: =IF(Setup!A17<>"",SUMIFS(F5:F255,D5:D255,"Added to Savings",I5:I255,Setup!A17)-SUMIFS(F5:F255,G5:G255,Setup!A17),"")
A17: =IF(F17<>"",ROW()-4,"") | L17: Savings 5 (balance) | M17: =IF(Setup!A17<>"",Setup!B17+(SUMIFS('April'!F5:F64,'April'!D5:D64,"Added to Savings",'April'!I5:I64,Setup!A17)+SUMIFS('May'!F5:F64,'May'!D5:D64,"Added to Savings",'May'!I5:I64,Setup!A17)+SUMIFS('June'!F5:F64,'June'!D5:D64,"Added to Savings",'June'!I5:I64,Setup!A17)+SUMIFS('July'!F5:F64,'July'!D5:D64,"Added to Savings",'July'!I5:I64,Setup!A17)+SUMIFS('August'!F5:F64,'August'!D5:D64,"Added to Savings",'August'!I5:I64,Setup!A17))-(SUMIFS('April'!F5:F64,'April'!G5:G64,Setup!A17)+SUMIFS('May'!F5:F64,'May'!G5:G64,Setup!A17)+SUMIFS('June'!F5:F64,'June'!G5:G64,Setup!A17)+SUMIFS('July'!F5:F64,'July'!G5:G64,Setup!A17)+SUMIFS('August'!F5:F64,'August'!G5:G64,Setup!A17)),"")
A18: =IF(F18<>"",ROW()-4,"") | L18: Fixed Bills Paid | M18: =SUMIF(D5:D255,"Fixed Bills",F5:F255)
A19: =IF(F19<>"",ROW()-4,"") | L19: Food & Dining | M19: =SUMIF(D5:D255,"Food & Dining",F5:F255)
A20: =IF(F20<>"",ROW()-4,"") | L20: Transport | M20: =SUMIF(D5:D255,"Transport & Fuel",F5:F255)
A21: =IF(F21<>"",ROW()-4,"") | L21: Groceries | M21: =SUMIF(D5:D255,"Groceries",F5:F255)
A22: =IF(F22<>"",ROW()-4,"") | L22: Shopping | M22: =SUMIF(D5:D255,"Shopping & Clothing",F5:F255)
A23: =IF(F23<>"",ROW()-4,"") | L23: Entertainment | M23: =SUMIF(D5:D255,"Entertainment & OTT",F5:F255)
A24: =IF(F24<>"",ROW()-4,"") | L24: Investment | M24: =SUMIF(D5:D255,"Investment",F5:F255)
A25: =IF(F25<>"",ROW()-4,"") | L25: Added to Savings | M25: =SUMIF(D5:D255,"Added to Savings",F5:F255)
A26: =IF(F26<>"",ROW()-4,"") | L26: CC Payments | M26: =SUMIF(D5:D255,"Credit Card Payment",F5:F255)
A27: =IF(F27<>"",ROW()-4,"") | L27: Miscellaneous | M27: =SUMIF(D5:D255,"Miscellaneous",F5:F255)
A28: =IF(F28<>"",ROW()-4,"")
A29: =IF(F29<>"",ROW()-4,"")
A30: =IF(F30<>"",ROW()-4,"")
A31: =IF(F31<>"",ROW()-4,"")
A32: =IF(F32<>"",ROW()-4,"")
A33: =IF(F33<>"",ROW()-4,"")
A34: =IF(F34<>"",ROW()-4,"")
A35: =IF(F35<>"",ROW()-4,"")
A36: =IF(F36<>"",ROW()-4,"")
A37: =IF(F37<>"",ROW()-4,"")
A38: =IF(F38<>"",ROW()-4,"")
A39: =IF(F39<>"",ROW()-4,"")
... A255: =IF(F255<>"",ROW()-4,"")
A256: TOTAL EXPENSES THIS MONTH | F256: =SUM(F5:F255)

Sheet September
A1: 📝 SEPTEMBER — EXPENSE LOG
A2: ℹ️ Date is DateTime. Category dropdown → Sub-category changes automatically. 'Added to Savings' → pick your saving account in Sub-category. CC spend → pick card in 'CC Name'. CC payment → increases card limit.
A4: # | B4: Date & Time | C4: Description | D4: Category | E4: Sub-category | F4: Amount (₹) | G4: Paid From | H4: CC Name | I4: Account | J4: Notes | L4: 📊 September Summary | M4: Amount (₹)
A5: =IF(F5<>"",ROW()-4,"") | L5: Total Expenses | M5: =F256
A6: =IF(F6<>"",ROW()-4,"") | L6: Income This Month | M6: =Income!E9
A7: =IF(F7<>"",ROW()-4,"") | L7: Net This Month | M7: =M6-M5
A8: =IF(F8<>"",ROW()-4,"") | L8: Savings 1 (this month) | M8: =IF(Setup!A13<>"",SUMIFS(F5:F255,D5:D255,"Added to Savings",I5:I255,Setup!A13)-SUMIFS(F5:F255,G5:G255,Setup!A13),"")
A9: =IF(F9<>"",ROW()-4,"") | L9: Savings 1 (balance) | M9: =IF(Setup!A13<>"",Setup!B13+(SUMIFS('April'!F5:F64,'April'!D5:D64,"Added to Savings",'April'!I5:I64,Setup!A13)+SUMIFS('May'!F5:F64,'May'!D5:D64,"Added to Savings",'May'!I5:I64,Setup!A13)+SUMIFS('June'!F5:F64,'June'!D5:D64,"Added to Savings",'June'!I5:I64,Setup!A13)+SUMIFS('July'!F5:F64,'July'!D5:D64,"Added to Savings",'July'!I5:I64,Setup!A13)+SUMIFS('August'!F5:F64,'August'!D5:D64,"Added to Savings",'August'!I5:I64,Setup!A13)+SUMIFS('September'!F5:F64,'September'!D5:D64,"Added to Savings",'September'!I5:I64,Setup!A13))-(SUMIFS('April'!F5:F64,'April'!G5:G64,Setup!A13)+SUMIFS('May'!F5:F64,'May'!G5:G64,Setup!A13)+SUMIFS('June'!F5:F64,'June'!G5:G64,Setup!A13)+SUMIFS('July'!F5:F64,'July'!G5:G64,Setup!A13)+SUMIFS('August'!F5:F64,'August'!G5:G64,Setup!A13)+SUMIFS('September'!F5:F64,'September'!G5:G64,Setup!A13)),"")
A10: =IF(F10<>"",ROW()-4,"") | L10: Savings 2 (this month) | M10: =IF(Setup!A14<>"",SUMIFS(F5:F255,D5:D255,"Added to Savings",I5:I255,Setup!A14)-SUMIFS(F5:F255,G5:G255,Setup!A14),"")
A11: =IF(F11<>"",ROW()-4,"") | L11: Savings 2 (balance) | M11: =IF(Setup!A14<>"",Setup!B14+(SUMIFS('April'!F5:F64,'April'!D5:D64,"Added to Savings",'April'!I5:I64,Setup!A14)+SUMIFS('May'!F5:F64,'May'!D5:D64,"Added to Savings",'May'!I5:I64,Setup!A14)+SUMIFS('June'!F5:F64,'June'!D5:D64,"Added to Savings",'June'!I5:I64,Setup!A14)+SUMIFS('July'!F5:F64,'July'!D5:D64,"Added to Savings",'July'!I5:I64,Setup!A14)+SUMIFS('August'!F5:F64,'August'!D5:D64,"Added to Savings",'August'!I5:I64,Setup!A14)+SUMIFS('September'!F5:F64,'September'!D5:D64,"Added to Savings",'September'!I5:I64,Setup!A14))-(SUMIFS('April'!F5:F64,'April'!G5:G64,Setup!A14)+SUMIFS('May'!F5:F64,'May'!G5:G64,Setup!A14)+SUMIFS('June'!F5:F64,'June'!G5:G64,Setup!A14)+SUMIFS('July'!F5:F64,'July'!G5:G64,Setup!A14)+SUMIFS('August'!F5:F64,'August'!G5:G64,Setup!A14)+SUMIFS('September'!F5:F64,'September'!G5:G64,Setup!A14)),"")
A12: =IF(F12<>"",ROW()-4,"") | L12: Savings 3 (this month) | M12: =IF(Setup!A15<>"",SUMIFS(F5:F255,D5:D255,"Added to Savings",I5:I255,Setup!A15)-SUMIFS(F5:F255,G5:G255,Setup!A15),"")
A13: =IF(F13<>"",ROW()-4,"") | L13: Savings 3 (balance) | M13: =IF(Setup!A15<>"",Setup!B15+(SUMIFS('April'!F5:F64,'April'!D5:D64,"Added to Savings",'April'!I5:I64,Setup!A15)+SUMIFS('May'!F5:F64,'May'!D5:D64,"Added to Savings",'May'!I5:I64,Setup!A15)+SUMIFS('June'!F5:F64,'June'!D5:D64,"Added to Savings",'June'!I5:I64,Setup!A15)+SUMIFS('July'!F5:F64,'July'!D5:D64,"Added to Savings",'July'!I5:I64,Setup!A15)+SUMIFS('August'!F5:F64,'August'!D5:D64,"Added to Savings",'August'!I5:I64,Setup!A15)+SUMIFS('September'!F5:F64,'September'!D5:D64,"Added to Savings",'September'!I5:I64,Setup!A15))-(SUMIFS('April'!F5:F64,'April'!G5:G64,Setup!A15)+SUMIFS('May'!F5:F64,'May'!G5:G64,Setup!A15)+SUMIFS('June'!F5:F64,'June'!G5:G64,Setup!A15)+SUMIFS('July'!F5:F64,'July'!G5:G64,Setup!A15)+SUMIFS('August'!F5:F64,'August'!G5:G64,Setup!A15)+SUMIFS('September'!F5:F64,'September'!G5:G64,Setup!A15)),"")
A14: =IF(F14<>"",ROW()-4,"") | L14: Savings 4 (this month) | M14: =IF(Setup!A16<>"",SUMIFS(F5:F255,D5:D255,"Added to Savings",I5:I255,Setup!A16)-SUMIFS(F5:F255,G5:G255,Setup!A16),"")
A15: =IF(F15<>"",ROW()-4,"") | L15: Savings 4 (balance) | M15: =IF(Setup!A16<>"",Setup!B16+(SUMIFS('April'!F5:F64,'April'!D5:D64,"Added to Savings",'April'!I5:I64,Setup!A16)+SUMIFS('May'!F5:F64,'May'!D5:D64,"Added to Savings",'May'!I5:I64,Setup!A16)+SUMIFS('June'!F5:F64,'June'!D5:D64,"Added to Savings",'June'!I5:I64,Setup!A16)+SUMIFS('July'!F5:F64,'July'!D5:D64,"Added to Savings",'July'!I5:I64,Setup!A16)+SUMIFS('August'!F5:F64,'August'!D5:D64,"Added to Savings",'August'!I5:I64,Setup!A16)+SUMIFS('September'!F5:F64,'September'!D5:D64,"Added to Savings",'September'!I5:I64,Setup!A16))-(SUMIFS('April'!F5:F64,'April'!G5:G64,Setup!A16)+SUMIFS('May'!F5:F64,'May'!G5:G64,Setup!A16)+SUMIFS('June'!F5:F64,'June'!G5:G64,Setup!A16)+SUMIFS('July'!F5:F64,'July'!G5:G64,Setup!A16)+SUMIFS('August'!F5:F64,'August'!G5:G64,Setup!A16)+SUMIFS('September'!F5:F64,'September'!G5:G64,Setup!A16)),"")
A16: =IF(F16<>"",ROW()-4,"") | L16: Savings 5 (this month) | M16: =IF(Setup!A17<>"",SUMIFS(F5:F255,D5:D255,"Added to Savings",I5:I255,Setup!A17)-SUMIFS(F5:F255,G5:G255,Setup!A17),"")
A17: =IF(F17<>"",ROW()-4,"") | L17: Savings 5 (balance) | M17: =IF(Setup!A17<>"",Setup!B17+(SUMIFS('April'!F5:F64,'April'!D5:D64,"Added to Savings",'April'!I5:I64,Setup!A17)+SUMIFS('May'!F5:F64,'May'!D5:D64,"Added to Savings",'May'!I5:I64,Setup!A17)+SUMIFS('June'!F5:F64,'June'!D5:D64,"Added to Savings",'June'!I5:I64,Setup!A17)+SUMIFS('July'!F5:F64,'July'!D5:D64,"Added to Savings",'July'!I5:I64,Setup!A17)+SUMIFS('August'!F5:F64,'August'!D5:D64,"Added to Savings",'August'!I5:I64,Setup!A17)+SUMIFS('September'!F5:F64,'September'!D5:D64,"Added to Savings",'September'!I5:I64,Setup!A17))-(SUMIFS('April'!F5:F64,'April'!G5:G64,Setup!A17)+SUMIFS('May'!F5:F64,'May'!G5:G64,Setup!A17)+SUMIFS('June'!F5:F64,'June'!G5:G64,Setup!A17)+SUMIFS('July'!F5:F64,'July'!G5:G64,Setup!A17)+SUMIFS('August'!F5:F64,'August'!G5:G64,Setup!A17)+SUMIFS('September'!F5:F64,'September'!G5:G64,Setup!A17)),"")
A18: =IF(F18<>"",ROW()-4,"") | L18: Fixed Bills Paid | M18: =SUMIF(D5:D255,"Fixed Bills",F5:F255)
A19: =IF(F19<>"",ROW()-4,"") | L19: Food & Dining | M19: =SUMIF(D5:D255,"Food & Dining",F5:F255)
A20: =IF(F20<>"",ROW()-4,"") | L20: Transport | M20: =SUMIF(D5:D255,"Transport & Fuel",F5:F255)
A21: =IF(F21<>"",ROW()-4,"") | L21: Groceries | M21: =SUMIF(D5:D255,"Groceries",F5:F255)
A22: =IF(F22<>"",ROW()-4,"") | L22: Shopping | M22: =SUMIF(D5:D255,"Shopping & Clothing",F5:F255)
A23: =IF(F23<>"",ROW()-4,"") | L23: Entertainment | M23: =SUMIF(D5:D255,"Entertainment & OTT",F5:F255)
A24: =IF(F24<>"",ROW()-4,"") | L24: Investment | M24: =SUMIF(D5:D255,"Investment",F5:F255)
A25: =IF(F25<>"",ROW()-4,"") | L25: Added to Savings | M25: =SUMIF(D5:D255,"Added to Savings",F5:F255)
A26: =IF(F26<>"",ROW()-4,"") | L26: CC Payments | M26: =SUMIF(D5:D255,"Credit Card Payment",F5:F255)
A27: =IF(F27<>"",ROW()-4,"") | L27: Miscellaneous | M27: =SUMIF(D5:D255,"Miscellaneous",F5:F255)
A28: =IF(F28<>"",ROW()-4,"")
A29: =IF(F29<>"",ROW()-4,"")
A30: =IF(F30<>"",ROW()-4,"")
A31: =IF(F31<>"",ROW()-4,"")
A32: =IF(F32<>"",ROW()-4,"")
A33: =IF(F33<>"",ROW()-4,"")
A34: =IF(F34<>"",ROW()-4,"")
A35: =IF(F35<>"",ROW()-4,"")
A36: =IF(F36<>"",ROW()-4,"")
A37: =IF(F37<>"",ROW()-4,"")
A38: =IF(F38<>"",ROW()-4,"")
A39: =IF(F39<>"",ROW()-4,"")
... A255: =IF(F255<>"",ROW()-4,"")
A256: TOTAL EXPENSES THIS MONTH | F256: =SUM(F5:F255)

Sheet October
A1: 📝 OCTOBER — EXPENSE LOG
A2: ℹ️ Date is DateTime. Category dropdown → Sub-category changes automatically. 'Added to Savings' → pick your saving account in Sub-category. CC spend → pick card in 'CC Name'. CC payment → increases card limit.
A4: # | B4: Date & Time | C4: Description | D4: Category | E4: Sub-category | F4: Amount (₹) | G4: Paid From | H4: CC Name | I4: Account | J4: Notes | L4: 📊 October Summary | M4: Amount (₹)
A5: =IF(F5<>"",ROW()-4,"") | L5: Total Expenses | M5: =F256
A6: =IF(F6<>"",ROW()-4,"") | L6: Income This Month | M6: =Income!E10
A7: =IF(F7<>"",ROW()-4,"") | L7: Net This Month | M7: =M6-M5
A8: =IF(F8<>"",ROW()-4,"") | L8: Savings 1 (this month) | M8: =IF(Setup!A13<>"",SUMIFS(F5:F255,D5:D255,"Added to Savings",I5:I255,Setup!A13)-SUMIFS(F5:F255,G5:G255,Setup!A13),"")
A9: =IF(F9<>"",ROW()-4,"") | L9: Savings 1 (balance) | M9: =IF(Setup!A13<>"",Setup!B13+(SUMIFS('April'!F5:F64,'April'!D5:D64,"Added to Savings",'April'!I5:I64,Setup!A13)+SUMIFS('May'!F5:F64,'May'!D5:D64,"Added to Savings",'May'!I5:I64,Setup!A13)+SUMIFS('June'!F5:F64,'June'!D5:D64,"Added to Savings",'June'!I5:I64,Setup!A13)+SUMIFS('July'!F5:F64,'July'!D5:D64,"Added to Savings",'July'!I5:I64,Setup!A13)+SUMIFS('August'!F5:F64,'August'!D5:D64,"Added to Savings",'August'!I5:I64,Setup!A13)+SUMIFS('September'!F5:F64,'September'!D5:D64,"Added to Savings",'September'!I5:I64,Setup!A13)+SUMIFS('October'!F5:F64,'October'!D5:D64,"Added to Savings",'October'!I5:I64,Setup!A13))-(SUMIFS('April'!F5:F64,'April'!G5:G64,Setup!A13)+SUMIFS('May'!F5:F64,'May'!G5:G64,Setup!A13)+SUMIFS('June'!F5:F64,'June'!G5:G64,Setup!A13)+SUMIFS('July'!F5:F64,'July'!G5:G64,Setup!A13)+SUMIFS('August'!F5:F64,'August'!G5:G64,Setup!A13)+SUMIFS('September'!F5:F64,'September'!G5:G64,Setup!A13)+SUMIFS('October'!F5:F64,'October'!G5:G64,Setup!A13)),"")
A10: =IF(F10<>"",ROW()-4,"") | L10: Savings 2 (this month) | M10: =IF(Setup!A14<>"",SUMIFS(F5:F255,D5:D255,"Added to Savings",I5:I255,Setup!A14)-SUMIFS(F5:F255,G5:G255,Setup!A14),"")
A11: =IF(F11<>"",ROW()-4,"") | L11: Savings 2 (balance) | M11: =IF(Setup!A14<>"",Setup!B14+(SUMIFS('April'!F5:F64,'April'!D5:D64,"Added to Savings",'April'!I5:I64,Setup!A14)+SUMIFS('May'!F5:F64,'May'!D5:D64,"Added to Savings",'May'!I5:I64,Setup!A14)+SUMIFS('June'!F5:F64,'June'!D5:D64,"Added to Savings",'June'!I5:I64,Setup!A14)+SUMIFS('July'!F5:F64,'July'!D5:D64,"Added to Savings",'July'!I5:I64,Setup!A14)+SUMIFS('August'!F5:F64,'August'!D5:D64,"Added to Savings",'August'!I5:I64,Setup!A14)+SUMIFS('September'!F5:F64,'September'!D5:D64,"Added to Savings",'September'!I5:I64,Setup!A14)+SUMIFS('October'!F5:F64,'October'!D5:D64,"Added to Savings",'October'!I5:I64,Setup!A14))-(SUMIFS('April'!F5:F64,'April'!G5:G64,Setup!A14)+SUMIFS('May'!F5:F64,'May'!G5:G64,Setup!A14)+SUMIFS('June'!F5:F64,'June'!G5:G64,Setup!A14)+SUMIFS('July'!F5:F64,'July'!G5:G64,Setup!A14)+SUMIFS('August'!F5:F64,'August'!G5:G64,Setup!A14)+SUMIFS('September'!F5:F64,'September'!G5:G64,Setup!A14)+SUMIFS('October'!F5:F64,'October'!G5:G64,Setup!A14)),"")
A12: =IF(F12<>"",ROW()-4,"") | L12: Savings 3 (this month) | M12: =IF(Setup!A15<>"",SUMIFS(F5:F255,D5:D255,"Added to Savings",I5:I255,Setup!A15)-SUMIFS(F5:F255,G5:G255,Setup!A15),"")
A13: =IF(F13<>"",ROW()-4,"") | L13: Savings 3 (balance) | M13: =IF(Setup!A15<>"",Setup!B15+(SUMIFS('April'!F5:F64,'April'!D5:D64,"Added to Savings",'April'!I5:I64,Setup!A15)+SUMIFS('May'!F5:F64,'May'!D5:D64,"Added to Savings",'May'!I5:I64,Setup!A15)+SUMIFS('June'!F5:F64,'June'!D5:D64,"Added to Savings",'June'!I5:I64,Setup!A15)+SUMIFS('July'!F5:F64,'July'!D5:D64,"Added to Savings",'July'!I5:I64,Setup!A15)+SUMIFS('August'!F5:F64,'August'!D5:D64,"Added to Savings",'August'!I5:I64,Setup!A15)+SUMIFS('September'!F5:F64,'September'!D5:D64,"Added to Savings",'September'!I5:I64,Setup!A15)+SUMIFS('October'!F5:F64,'October'!D5:D64,"Added to Savings",'October'!I5:I64,Setup!A15))-(SUMIFS('April'!F5:F64,'April'!G5:G64,Setup!A15)+SUMIFS('May'!F5:F64,'May'!G5:G64,Setup!A15)+SUMIFS('June'!F5:F64,'June'!G5:G64,Setup!A15)+SUMIFS('July'!F5:F64,'July'!G5:G64,Setup!A15)+SUMIFS('August'!F5:F64,'August'!G5:G64,Setup!A15)+SUMIFS('September'!F5:F64,'September'!G5:G64,Setup!A15)+SUMIFS('October'!F5:F64,'October'!G5:G64,Setup!A15)),"")
A14: =IF(F14<>"",ROW()-4,"") | L14: Savings 4 (this month) | M14: =IF(Setup!A16<>"",SUMIFS(F5:F255,D5:D255,"Added to Savings",I5:I255,Setup!A16)-SUMIFS(F5:F255,G5:G255,Setup!A16),"")
A15: =IF(F15<>"",ROW()-4,"") | L15: Savings 4 (balance) | M15: =IF(Setup!A16<>"",Setup!B16+(SUMIFS('April'!F5:F64,'April'!D5:D64,"Added to Savings",'April'!I5:I64,Setup!A16)+SUMIFS('May'!F5:F64,'May'!D5:D64,"Added to Savings",'May'!I5:I64,Setup!A16)+SUMIFS('June'!F5:F64,'June'!D5:D64,"Added to Savings",'June'!I5:I64,Setup!A16)+SUMIFS('July'!F5:F64,'July'!D5:D64,"Added to Savings",'July'!I5:I64,Setup!A16)+SUMIFS('August'!F5:F64,'August'!D5:D64,"Added to Savings",'August'!I5:I64,Setup!A16)+SUMIFS('September'!F5:F64,'September'!D5:D64,"Added to Savings",'September'!I5:I64,Setup!A16)+SUMIFS('October'!F5:F64,'October'!D5:D64,"Added to Savings",'October'!I5:I64,Setup!A16))-(SUMIFS('April'!F5:F64,'April'!G5:G64,Setup!A16)+SUMIFS('May'!F5:F64,'May'!G5:G64,Setup!A16)+SUMIFS('June'!F5:F64,'June'!G5:G64,Setup!A16)+SUMIFS('July'!F5:F64,'July'!G5:G64,Setup!A16)+SUMIFS('August'!F5:F64,'August'!G5:G64,Setup!A16)+SUMIFS('September'!F5:F64,'September'!G5:G64,Setup!A16)+SUMIFS('October'!F5:F64,'October'!G5:G64,Setup!A16)),"")
A16: =IF(F16<>"",ROW()-4,"") | L16: Savings 5 (this month) | M16: =IF(Setup!A17<>"",SUMIFS(F5:F255,D5:D255,"Added to Savings",I5:I255,Setup!A17)-SUMIFS(F5:F255,G5:G255,Setup!A17),"")
A17: =IF(F17<>"",ROW()-4,"") | L17: Savings 5 (balance) | M17: =IF(Setup!A17<>"",Setup!B17+(SUMIFS('April'!F5:F64,'April'!D5:D64,"Added to Savings",'April'!I5:I64,Setup!A17)+SUMIFS('May'!F5:F64,'May'!D5:D64,"Added to Savings",'May'!I5:I64,Setup!A17)+SUMIFS('June'!F5:F64,'June'!D5:D64,"Added to Savings",'June'!I5:I64,Setup!A17)+SUMIFS('July'!F5:F64,'July'!D5:D64,"Added to Savings",'July'!I5:I64,Setup!A17)+SUMIFS('August'!F5:F64,'August'!D5:D64,"Added to Savings",'August'!I5:I64,Setup!A17)+SUMIFS('September'!F5:F64,'September'!D5:D64,"Added to Savings",'September'!I5:I64,Setup!A17)+SUMIFS('October'!F5:F64,'October'!D5:D64,"Added to Savings",'October'!I5:I64,Setup!A17))-(SUMIFS('April'!F5:F64,'April'!G5:G64,Setup!A17)+SUMIFS('May'!F5:F64,'May'!G5:G64,Setup!A17)+SUMIFS('June'!F5:F64,'June'!G5:G64,Setup!A17)+SUMIFS('July'!F5:F64,'July'!G5:G64,Setup!A17)+SUMIFS('August'!F5:F64,'August'!G5:G64,Setup!A17)+SUMIFS('September'!F5:F64,'September'!G5:G64,Setup!A17)+SUMIFS('October'!F5:F64,'October'!G5:G64,Setup!A17)),"")
A18: =IF(F18<>"",ROW()-4,"") | L18: Fixed Bills Paid | M18: =SUMIF(D5:D255,"Fixed Bills",F5:F255)
A19: =IF(F19<>"",ROW()-4,"") | L19: Food & Dining | M19: =SUMIF(D5:D255,"Food & Dining",F5:F255)
A20: =IF(F20<>"",ROW()-4,"") | L20: Transport | M20: =SUMIF(D5:D255,"Transport & Fuel",F5:F255)
A21: =IF(F21<>"",ROW()-4,"") | L21: Groceries | M21: =SUMIF(D5:D255,"Groceries",F5:F255)
A22: =IF(F22<>"",ROW()-4,"") | L22: Shopping | M22: =SUMIF(D5:D255,"Shopping & Clothing",F5:F255)
A23: =IF(F23<>"",ROW()-4,"") | L23: Entertainment | M23: =SUMIF(D5:D255,"Entertainment & OTT",F5:F255)
A24: =IF(F24<>"",ROW()-4,"") | L24: Investment | M24: =SUMIF(D5:D255,"Investment",F5:F255)
A25: =IF(F25<>"",ROW()-4,"") | L25: Added to Savings | M25: =SUMIF(D5:D255,"Added to Savings",F5:F255)
A26: =IF(F26<>"",ROW()-4,"") | L26: CC Payments | M26: =SUMIF(D5:D255,"Credit Card Payment",F5:F255)
A27: =IF(F27<>"",ROW()-4,"") | L27: Miscellaneous | M27: =SUMIF(D5:D255,"Miscellaneous",F5:F255)
A28: =IF(F28<>"",ROW()-4,"")
A29: =IF(F29<>"",ROW()-4,"")
A30: =IF(F30<>"",ROW()-4,"")
A31: =IF(F31<>"",ROW()-4,"")
A32: =IF(F32<>"",ROW()-4,"")
A33: =IF(F33<>"",ROW()-4,"")
A34: =IF(F34<>"",ROW()-4,"")
A35: =IF(F35<>"",ROW()-4,"")
A36: =IF(F36<>"",ROW()-4,"")
A37: =IF(F37<>"",ROW()-4,"")
A38: =IF(F38<>"",ROW()-4,"")
A39: =IF(F39<>"",ROW()-4,"")
... A255: =IF(F255<>"",ROW()-4,"")
A256: TOTAL EXPENSES THIS MONTH | F256: =SUM(F5:F255)

Sheet November
A1: 📝 NOVEMBER — EXPENSE LOG
A2: ℹ️ Date is DateTime. Category dropdown → Sub-category changes automatically. 'Added to Savings' → pick your saving account in Sub-category. CC spend → pick card in 'CC Name'. CC payment → increases card limit.
A4: # | B4: Date & Time | C4: Description | D4: Category | E4: Sub-category | F4: Amount (₹) | G4: Paid From | H4: CC Name | I4: Account | J4: Notes | L4: 📊 November Summary | M4: Amount (₹)
A5: =IF(F5<>"",ROW()-4,"") | L5: Total Expenses | M5: =F256
A6: =IF(F6<>"",ROW()-4,"") | L6: Income This Month | M6: =Income!E11
A7: =IF(F7<>"",ROW()-4,"") | L7: Net This Month | M7: =M6-M5
A8: =IF(F8<>"",ROW()-4,"") | L8: Savings 1 (this month) | M8: =IF(Setup!A13<>"",SUMIFS(F5:F255,D5:D255,"Added to Savings",I5:I255,Setup!A13)-SUMIFS(F5:F255,G5:G255,Setup!A13),"")
A9: =IF(F9<>"",ROW()-4,"") | L9: Savings 1 (balance) | M9: =IF(Setup!A13<>"",Setup!B13+(SUMIFS('April'!F5:F64,'April'!D5:D64,"Added to Savings",'April'!I5:I64,Setup!A13)+SUMIFS('May'!F5:F64,'May'!D5:D64,"Added to Savings",'May'!I5:I64,Setup!A13)+SUMIFS('June'!F5:F64,'June'!D5:D64,"Added to Savings",'June'!I5:I64,Setup!A13)+SUMIFS('July'!F5:F64,'July'!D5:D64,"Added to Savings",'July'!I5:I64,Setup!A13)+SUMIFS('August'!F5:F64,'August'!D5:D64,"Added to Savings",'August'!I5:I64,Setup!A13)+SUMIFS('September'!F5:F64,'September'!D5:D64,"Added to Savings",'September'!I5:I64,Setup!A13)+SUMIFS('October'!F5:F64,'October'!D5:D64,"Added to Savings",'October'!I5:I64,Setup!A13)+SUMIFS('November'!F5:F64,'November'!D5:D64,"Added to Savings",'November'!I5:I64,Setup!A13))-(SUMIFS('April'!F5:F64,'April'!G5:G64,Setup!A13)+SUMIFS('May'!F5:F64,'May'!G5:G64,Setup!A13)+SUMIFS('June'!F5:F64,'June'!G5:G64,Setup!A13)+SUMIFS('July'!F5:F64,'July'!G5:G64,Setup!A13)+SUMIFS('August'!F5:F64,'August'!G5:G64,Setup!A13)+SUMIFS('September'!F5:F64,'September'!G5:G64,Setup!A13)+SUMIFS('October'!F5:F64,'October'!G5:G64,Setup!A13)+SUMIFS('November'!F5:F64,'November'!G5:G64,Setup!A13)),"")
A10: =IF(F10<>"",ROW()-4,"") | L10: Savings 2 (this month) | M10: =IF(Setup!A14<>"",SUMIFS(F5:F255,D5:D255,"Added to Savings",I5:I255,Setup!A14)-SUMIFS(F5:F255,G5:G255,Setup!A14),"")
A11: =IF(F11<>"",ROW()-4,"") | L11: Savings 2 (balance) | M11: =IF(Setup!A14<>"",Setup!B14+(SUMIFS('April'!F5:F64,'April'!D5:D64,"Added to Savings",'April'!I5:I64,Setup!A14)+SUMIFS('May'!F5:F64,'May'!D5:D64,"Added to Savings",'May'!I5:I64,Setup!A14)+SUMIFS('June'!F5:F64,'June'!D5:D64,"Added to Savings",'June'!I5:I64,Setup!A14)+SUMIFS('July'!F5:F64,'July'!D5:D64,"Added to Savings",'July'!I5:I64,Setup!A14)+SUMIFS('August'!F5:F64,'August'!D5:D64,"Added to Savings",'August'!I5:I64,Setup!A14)+SUMIFS('September'!F5:F64,'September'!D5:D64,"Added to Savings",'September'!I5:I64,Setup!A14)+SUMIFS('October'!F5:F64,'October'!D5:D64,"Added to Savings",'October'!I5:I64,Setup!A14)+SUMIFS('November'!F5:F64,'November'!D5:D64,"Added to Savings",'November'!I5:I64,Setup!A14))-(SUMIFS('April'!F5:F64,'April'!G5:G64,Setup!A14)+SUMIFS('May'!F5:F64,'May'!G5:G64,Setup!A14)+SUMIFS('June'!F5:F64,'June'!G5:G64,Setup!A14)+SUMIFS('July'!F5:F64,'July'!G5:G64,Setup!A14)+SUMIFS('August'!F5:F64,'August'!G5:G64,Setup!A14)+SUMIFS('September'!F5:F64,'September'!G5:G64,Setup!A14)+SUMIFS('October'!F5:F64,'October'!G5:G64,Setup!A14)+SUMIFS('November'!F5:F64,'November'!G5:G64,Setup!A14)),"")
A12: =IF(F12<>"",ROW()-4,"") | L12: Savings 3 (this month) | M12: =IF(Setup!A15<>"",SUMIFS(F5:F255,D5:D255,"Added to Savings",I5:I255,Setup!A15)-SUMIFS(F5:F255,G5:G255,Setup!A15),"")
A13: =IF(F13<>"",ROW()-4,"") | L13: Savings 3 (balance) | M13: =IF(Setup!A15<>"",Setup!B15+(SUMIFS('April'!F5:F64,'April'!D5:D64,"Added to Savings",'April'!I5:I64,Setup!A15)+SUMIFS('May'!F5:F64,'May'!D5:D64,"Added to Savings",'May'!I5:I64,Setup!A15)+SUMIFS('June'!F5:F64,'June'!D5:D64,"Added to Savings",'June'!I5:I64,Setup!A15)+SUMIFS('July'!F5:F64,'July'!D5:D64,"Added to Savings",'July'!I5:I64,Setup!A15)+SUMIFS('August'!F5:F64,'August'!D5:D64,"Added to Savings",'August'!I5:I64,Setup!A15)+SUMIFS('September'!F5:F64,'September'!D5:D64,"Added to Savings",'September'!I5:I64,Setup!A15)+SUMIFS('October'!F5:F64,'October'!D5:D64,"Added to Savings",'October'!I5:I64,Setup!A15)+SUMIFS('November'!F5:F64,'November'!D5:D64,"Added to Savings",'November'!I5:I64,Setup!A15))-(SUMIFS('April'!F5:F64,'April'!G5:G64,Setup!A15)+SUMIFS('May'!F5:F64,'May'!G5:G64,Setup!A15)+SUMIFS('June'!F5:F64,'June'!G5:G64,Setup!A15)+SUMIFS('July'!F5:F64,'July'!G5:G64,Setup!A15)+SUMIFS('August'!F5:F64,'August'!G5:G64,Setup!A15)+SUMIFS('September'!F5:F64,'September'!G5:G64,Setup!A15)+SUMIFS('October'!F5:F64,'October'!G5:G64,Setup!A15)+SUMIFS('November'!F5:F64,'November'!G5:G64,Setup!A15)),"")
A14: =IF(F14<>"",ROW()-4,"") | L14: Savings 4 (this month) | M14: =IF(Setup!A16<>"",SUMIFS(F5:F255,D5:D255,"Added to Savings",I5:I255,Setup!A16)-SUMIFS(F5:F255,G5:G255,Setup!A16),"")
A15: =IF(F15<>"",ROW()-4,"") | L15: Savings 4 (balance) | M15: =IF(Setup!A16<>"",Setup!B16+(SUMIFS('April'!F5:F64,'April'!D5:D64,"Added to Savings",'April'!I5:I64,Setup!A16)+SUMIFS('May'!F5:F64,'May'!D5:D64,"Added to Savings",'May'!I5:I64,Setup!A16)+SUMIFS('June'!F5:F64,'June'!D5:D64,"Added to Savings",'June'!I5:I64,Setup!A16)+SUMIFS('July'!F5:F64,'July'!D5:D64,"Added to Savings",'July'!I5:I64,Setup!A16)+SUMIFS('August'!F5:F64,'August'!D5:D64,"Added to Savings",'August'!I5:I64,Setup!A16)+SUMIFS('September'!F5:F64,'September'!D5:D64,"Added to Savings",'September'!I5:I64,Setup!A16)+SUMIFS('October'!F5:F64,'October'!D5:D64,"Added to Savings",'October'!I5:I64,Setup!A16)+SUMIFS('November'!F5:F64,'November'!D5:D64,"Added to Savings",'November'!I5:I64,Setup!A16))-(SUMIFS('April'!F5:F64,'April'!G5:G64,Setup!A16)+SUMIFS('May'!F5:F64,'May'!G5:G64,Setup!A16)+SUMIFS('June'!F5:F64,'June'!G5:G64,Setup!A16)+SUMIFS('July'!F5:F64,'July'!G5:G64,Setup!A16)+SUMIFS('August'!F5:F64,'August'!G5:G64,Setup!A16)+SUMIFS('September'!F5:F64,'September'!G5:G64,Setup!A16)+SUMIFS('October'!F5:F64,'October'!G5:G64,Setup!A16)+SUMIFS('November'!F5:F64,'November'!G5:G64,Setup!A16)),"")
A16: =IF(F16<>"",ROW()-4,"") | L16: Savings 5 (this month) | M16: =IF(Setup!A17<>"",SUMIFS(F5:F255,D5:D255,"Added to Savings",I5:I255,Setup!A17)-SUMIFS(F5:F255,G5:G255,Setup!A17),"")
A17: =IF(F17<>"",ROW()-4,"") | L17: Savings 5 (balance) | M17: =IF(Setup!A17<>"",Setup!B17+(SUMIFS('April'!F5:F64,'April'!D5:D64,"Added to Savings",'April'!I5:I64,Setup!A17)+SUMIFS('May'!F5:F64,'May'!D5:D64,"Added to Savings",'May'!I5:I64,Setup!A17)+SUMIFS('June'!F5:F64,'June'!D5:D64,"Added to Savings",'June'!I5:I64,Setup!A17)+SUMIFS('July'!F5:F64,'July'!D5:D64,"Added to Savings",'July'!I5:I64,Setup!A17)+SUMIFS('August'!F5:F64,'August'!D5:D64,"Added to Savings",'August'!I5:I64,Setup!A17)+SUMIFS('September'!F5:F64,'September'!D5:D64,"Added to Savings",'September'!I5:I64,Setup!A17)+SUMIFS('October'!F5:F64,'October'!D5:D64,"Added to Savings",'October'!I5:I64,Setup!A17)+SUMIFS('November'!F5:F64,'November'!D5:D64,"Added to Savings",'November'!I5:I64,Setup!A17))-(SUMIFS('April'!F5:F64,'April'!G5:G64,Setup!A17)+SUMIFS('May'!F5:F64,'May'!G5:G64,Setup!A17)+SUMIFS('June'!F5:F64,'June'!G5:G64,Setup!A17)+SUMIFS('July'!F5:F64,'July'!G5:G64,Setup!A17)+SUMIFS('August'!F5:F64,'August'!G5:G64,Setup!A17)+SUMIFS('September'!F5:F64,'September'!G5:G64,Setup!A17)+SUMIFS('October'!F5:F64,'October'!G5:G64,Setup!A17)+SUMIFS('November'!F5:F64,'November'!G5:G64,Setup!A17)),"")
A18: =IF(F18<>"",ROW()-4,"") | L18: Fixed Bills Paid | M18: =SUMIF(D5:D255,"Fixed Bills",F5:F255)
A19: =IF(F19<>"",ROW()-4,"") | L19: Food & Dining | M19: =SUMIF(D5:D255,"Food & Dining",F5:F255)
A20: =IF(F20<>"",ROW()-4,"") | L20: Transport | M20: =SUMIF(D5:D255,"Transport & Fuel",F5:F255)
A21: =IF(F21<>"",ROW()-4,"") | L21: Groceries | M21: =SUMIF(D5:D255,"Groceries",F5:F255)
A22: =IF(F22<>"",ROW()-4,"") | L22: Shopping | M22: =SUMIF(D5:D255,"Shopping & Clothing",F5:F255)
A23: =IF(F23<>"",ROW()-4,"") | L23: Entertainment | M23: =SUMIF(D5:D255,"Entertainment & OTT",F5:F255)
A24: =IF(F24<>"",ROW()-4,"") | L24: Investment | M24: =SUMIF(D5:D255,"Investment",F5:F255)
A25: =IF(F25<>"",ROW()-4,"") | L25: Added to Savings | M25: =SUMIF(D5:D255,"Added to Savings",F5:F255)
A26: =IF(F26<>"",ROW()-4,"") | L26: CC Payments | M26: =SUMIF(D5:D255,"Credit Card Payment",F5:F255)
A27: =IF(F27<>"",ROW()-4,"") | L27: Miscellaneous | M27: =SUMIF(D5:D255,"Miscellaneous",F5:F255)
A28: =IF(F28<>"",ROW()-4,"")
A29: =IF(F29<>"",ROW()-4,"")
A30: =IF(F30<>"",ROW()-4,"")
A31: =IF(F31<>"",ROW()-4,"")
A32: =IF(F32<>"",ROW()-4,"")
A33: =IF(F33<>"",ROW()-4,"")
A34: =IF(F34<>"",ROW()-4,"")
A35: =IF(F35<>"",ROW()-4,"")
A36: =IF(F36<>"",ROW()-4,"")
A37: =IF(F37<>"",ROW()-4,"")
A38: =IF(F38<>"",ROW()-4,"")
A39: =IF(F39<>"",ROW()-4,"")
... A255: =IF(F255<>"",ROW()-4,"")
A256: TOTAL EXPENSES THIS MONTH | F256: =SUM(F5:F255)

Sheet December
A1: 📝 DECEMBER — EXPENSE LOG
A2: ℹ️ Date is DateTime. Category dropdown → Sub-category changes automatically. 'Added to Savings' → pick your saving account in Sub-category. CC spend → pick card in 'CC Name'. CC payment → increases card limit.
A4: # | B4: Date & Time | C4: Description | D4: Category | E4: Sub-category | F4: Amount (₹) | G4: Paid From | H4: CC Name | I4: Account | J4: Notes | L4: 📊 December Summary | M4: Amount (₹)
A5: =IF(F5<>"",ROW()-4,"") | L5: Total Expenses | M5: =F256
A6: =IF(F6<>"",ROW()-4,"") | L6: Income This Month | M6: =Income!E12
A7: =IF(F7<>"",ROW()-4,"") | L7: Net This Month | M7: =M6-M5
A8: =IF(F8<>"",ROW()-4,"") | L8: Savings 1 (this month) | M8: =IF(Setup!A13<>"",SUMIFS(F5:F255,D5:D255,"Added to Savings",I5:I255,Setup!A13)-SUMIFS(F5:F255,G5:G255,Setup!A13),"")
A9: =IF(F9<>"",ROW()-4,"") | L9: Savings 1 (balance) | M9: =IF(Setup!A13<>"",Setup!B13+(SUMIFS('April'!F5:F64,'April'!D5:D64,"Added to Savings",'April'!I5:I64,Setup!A13)+SUMIFS('May'!F5:F64,'May'!D5:D64,"Added to Savings",'May'!I5:I64,Setup!A13)+SUMIFS('June'!F5:F64,'June'!D5:D64,"Added to Savings",'June'!I5:I64,Setup!A13)+SUMIFS('July'!F5:F64,'July'!D5:D64,"Added to Savings",'July'!I5:I64,Setup!A13)+SUMIFS('August'!F5:F64,'August'!D5:D64,"Added to Savings",'August'!I5:I64,Setup!A13)+SUMIFS('September'!F5:F64,'September'!D5:D64,"Added to Savings",'September'!I5:I64,Setup!A13)+SUMIFS('October'!F5:F64,'October'!D5:D64,"Added to Savings",'October'!I5:I64,Setup!A13)+SUMIFS('November'!F5:F64,'November'!D5:D64,"Added to Savings",'November'!I5:I64,Setup!A13)+SUMIFS('December'!F5:F64,'December'!D5:D64,"Added to Savings",'December'!I5:I64,Setup!A13))-(SUMIFS('April'!F5:F64,'April'!G5:G64,Setup!A13)+SUMIFS('May'!F5:F64,'May'!G5:G64,Setup!A13)+SUMIFS('June'!F5:F64,'June'!G5:G64,Setup!A13)+SUMIFS('July'!F5:F64,'July'!G5:G64,Setup!A13)+SUMIFS('August'!F5:F64,'August'!G5:G64,Setup!A13)+SUMIFS('September'!F5:F64,'September'!G5:G64,Setup!A13)+SUMIFS('October'!F5:F64,'October'!G5:G64,Setup!A13)+SUMIFS('November'!F5:F64,'November'!G5:G64,Setup!A13)+SUMIFS('December'!F5:F64,'December'!G5:G64,Setup!A13)),"")
A10: =IF(F10<>"",ROW()-4,"") | L10: Savings 2 (this month) | M10: =IF(Setup!A14<>"",SUMIFS(F5:F255,D5:D255,"Added to Savings",I5:I255,Setup!A14)-SUMIFS(F5:F255,G5:G255,Setup!A14),"")
A11: =IF(F11<>"",ROW()-4,"") | L11: Savings 2 (balance) | M11: =IF(Setup!A14<>"",Setup!B14+(SUMIFS('April'!F5:F64,'April'!D5:D64,"Added to Savings",'April'!I5:I64,Setup!A14)+SUMIFS('May'!F5:F64,'May'!D5:D64,"Added to Savings",'May'!I5:I64,Setup!A14)+SUMIFS('June'!F5:F64,'June'!D5:D64,"Added to Savings",'June'!I5:I64,Setup!A14)+SUMIFS('July'!F5:F64,'July'!D5:D64,"Added to Savings",'July'!I5:I64,Setup!A14)+SUMIFS('August'!F5:F64,'August'!D5:D64,"Added to Savings",'August'!I5:I64,Setup!A14)+SUMIFS('September'!F5:F64,'September'!D5:D64,"Added to Savings",'September'!I5:I64,Setup!A14)+SUMIFS('October'!F5:F64,'October'!D5:D64,"Added to Savings",'October'!I5:I64,Setup!A14)+SUMIFS('November'!F5:F64,'November'!D5:D64,"Added to Savings",'November'!I5:I64,Setup!A14)+SUMIFS('December'!F5:F64,'December'!D5:D64,"Added to Savings",'December'!I5:I64,Setup!A14))-(SUMIFS('April'!F5:F64,'April'!G5:G64,Setup!A14)+SUMIFS('May'!F5:F64,'May'!G5:G64,Setup!A14)+SUMIFS('June'!F5:F64,'June'!G5:G64,Setup!A14)+SUMIFS('July'!F5:F64,'July'!G5:G64,Setup!A14)+SUMIFS('August'!F5:F64,'August'!G5:G64,Setup!A14)+SUMIFS('September'!F5:F64,'September'!G5:G64,Setup!A14)+SUMIFS('October'!F5:F64,'October'!G5:G64,Setup!A14)+SUMIFS('November'!F5:F64,'November'!G5:G64,Setup!A14)+SUMIFS('December'!F5:F64,'December'!G5:G64,Setup!A14)),"")
A12: =IF(F12<>"",ROW()-4,"") | L12: Savings 3 (this month) | M12: =IF(Setup!A15<>"",SUMIFS(F5:F255,D5:D255,"Added to Savings",I5:I255,Setup!A15)-SUMIFS(F5:F255,G5:G255,Setup!A15),"")
A13: =IF(F13<>"",ROW()-4,"") | L13: Savings 3 (balance) | M13: =IF(Setup!A15<>"",Setup!B15+(SUMIFS('April'!F5:F64,'April'!D5:D64,"Added to Savings",'April'!I5:I64,Setup!A15)+SUMIFS('May'!F5:F64,'May'!D5:D64,"Added to Savings",'May'!I5:I64,Setup!A15)+SUMIFS('June'!F5:F64,'June'!D5:D64,"Added to Savings",'June'!I5:I64,Setup!A15)+SUMIFS('July'!F5:F64,'July'!D5:D64,"Added to Savings",'July'!I5:I64,Setup!A15)+SUMIFS('August'!F5:F64,'August'!D5:D64,"Added to Savings",'August'!I5:I64,Setup!A15)+SUMIFS('September'!F5:F64,'September'!D5:D64,"Added to Savings",'September'!I5:I64,Setup!A15)+SUMIFS('October'!F5:F64,'October'!D5:D64,"Added to Savings",'October'!I5:I64,Setup!A15)+SUMIFS('November'!F5:F64,'November'!D5:D64,"Added to Savings",'November'!I5:I64,Setup!A15)+SUMIFS('December'!F5:F64,'December'!D5:D64,"Added to Savings",'December'!I5:I64,Setup!A15))-(SUMIFS('April'!F5:F64,'April'!G5:G64,Setup!A15)+SUMIFS('May'!F5:F64,'May'!G5:G64,Setup!A15)+SUMIFS('June'!F5:F64,'June'!G5:G64,Setup!A15)+SUMIFS('July'!F5:F64,'July'!G5:G64,Setup!A15)+SUMIFS('August'!F5:F64,'August'!G5:G64,Setup!A15)+SUMIFS('September'!F5:F64,'September'!G5:G64,Setup!A15)+SUMIFS('October'!F5:F64,'October'!G5:G64,Setup!A15)+SUMIFS('November'!F5:F64,'November'!G5:G64,Setup!A15)+SUMIFS('December'!F5:F64,'December'!G5:G64,Setup!A15)),"")
A14: =IF(F14<>"",ROW()-4,"") | L14: Savings 4 (this month) | M14: =IF(Setup!A16<>"",SUMIFS(F5:F255,D5:D255,"Added to Savings",I5:I255,Setup!A16)-SUMIFS(F5:F255,G5:G255,Setup!A16),"")
A15: =IF(F15<>"",ROW()-4,"") | L15: Savings 4 (balance) | M15: =IF(Setup!A16<>"",Setup!B16+(SUMIFS('April'!F5:F64,'April'!D5:D64,"Added to Savings",'April'!I5:I64,Setup!A16)+SUMIFS('May'!F5:F64,'May'!D5:D64,"Added to Savings",'May'!I5:I64,Setup!A16)+SUMIFS('June'!F5:F64,'June'!D5:D64,"Added to Savings",'June'!I5:I64,Setup!A16)+SUMIFS('July'!F5:F64,'July'!D5:D64,"Added to Savings",'July'!I5:I64,Setup!A16)+SUMIFS('August'!F5:F64,'August'!D5:D64,"Added to Savings",'August'!I5:I64,Setup!A16)+SUMIFS('September'!F5:F64,'September'!D5:D64,"Added to Savings",'September'!I5:I64,Setup!A16)+SUMIFS('October'!F5:F64,'October'!D5:D64,"Added to Savings",'October'!I5:I64,Setup!A16)+SUMIFS('November'!F5:F64,'November'!D5:D64,"Added to Savings",'November'!I5:I64,Setup!A16)+SUMIFS('December'!F5:F64,'December'!D5:D64,"Added to Savings",'December'!I5:I64,Setup!A16))-(SUMIFS('April'!F5:F64,'April'!G5:G64,Setup!A16)+SUMIFS('May'!F5:F64,'May'!G5:G64,Setup!A16)+SUMIFS('June'!F5:F64,'June'!G5:G64,Setup!A16)+SUMIFS('July'!F5:F64,'July'!G5:G64,Setup!A16)+SUMIFS('August'!F5:F64,'August'!G5:G64,Setup!A16)+SUMIFS('September'!F5:F64,'September'!G5:G64,Setup!A16)+SUMIFS('October'!F5:F64,'October'!G5:G64,Setup!A16)+SUMIFS('November'!F5:F64,'November'!G5:G64,Setup!A16)+SUMIFS('December'!F5:F64,'December'!G5:G64,Setup!A16)),"")
A16: =IF(F16<>"",ROW()-4,"") | L16: Savings 5 (this month) | M16: =IF(Setup!A17<>"",SUMIFS(F5:F255,D5:D255,"Added to Savings",I5:I255,Setup!A17)-SUMIFS(F5:F255,G5:G255,Setup!A17),"")
A17: =IF(F17<>"",ROW()-4,"") | L17: Savings 5 (balance) | M17: =IF(Setup!A17<>"",Setup!B17+(SUMIFS('April'!F5:F64,'April'!D5:D64,"Added to Savings",'April'!I5:I64,Setup!A17)+SUMIFS('May'!F5:F64,'May'!D5:D64,"Added to Savings",'May'!I5:I64,Setup!A17)+SUMIFS('June'!F5:F64,'June'!D5:D64,"Added to Savings",'June'!I5:I64,Setup!A17)+SUMIFS('July'!F5:F64,'July'!D5:D64,"Added to Savings",'July'!I5:I64,Setup!A17)+SUMIFS('August'!F5:F64,'August'!D5:D64,"Added to Savings",'August'!I5:I64,Setup!A17)+SUMIFS('September'!F5:F64,'September'!D5:D64,"Added to Savings",'September'!I5:I64,Setup!A17)+SUMIFS('October'!F5:F64,'October'!D5:D64,"Added to Savings",'October'!I5:I64,Setup!A17)+SUMIFS('November'!F5:F64,'November'!D5:D64,"Added to Savings",'November'!I5:I64,Setup!A17)+SUMIFS('December'!F5:F64,'December'!D5:D64,"Added to Savings",'December'!I5:I64,Setup!A17))-(SUMIFS('April'!F5:F64,'April'!G5:G64,Setup!A17)+SUMIFS('May'!F5:F64,'May'!G5:G64,Setup!A17)+SUMIFS('June'!F5:F64,'June'!G5:G64,Setup!A17)+SUMIFS('July'!F5:F64,'July'!G5:G64,Setup!A17)+SUMIFS('August'!F5:F64,'August'!G5:G64,Setup!A17)+SUMIFS('September'!F5:F64,'September'!G5:G64,Setup!A17)+SUMIFS('October'!F5:F64,'October'!G5:G64,Setup!A17)+SUMIFS('November'!F5:F64,'November'!G5:G64,Setup!A17)+SUMIFS('December'!F5:F64,'December'!G5:G64,Setup!A17)),"")
A18: =IF(F18<>"",ROW()-4,"") | L18: Fixed Bills Paid | M18: =SUMIF(D5:D255,"Fixed Bills",F5:F255)
A19: =IF(F19<>"",ROW()-4,"") | L19: Food & Dining | M19: =SUMIF(D5:D255,"Food & Dining",F5:F255)
A20: =IF(F20<>"",ROW()-4,"") | L20: Transport | M20: =SUMIF(D5:D255,"Transport & Fuel",F5:F255)
A21: =IF(F21<>"",ROW()-4,"") | L21: Groceries | M21: =SUMIF(D5:D255,"Groceries",F5:F255)
A22: =IF(F22<>"",ROW()-4,"") | L22: Shopping | M22: =SUMIF(D5:D255,"Shopping & Clothing",F5:F255)
A23: =IF(F23<>"",ROW()-4,"") | L23: Entertainment | M23: =SUMIF(D5:D255,"Entertainment & OTT",F5:F255)
A24: =IF(F24<>"",ROW()-4,"") | L24: Investment | M24: =SUMIF(D5:D255,"Investment",F5:F255)
A25: =IF(F25<>"",ROW()-4,"") | L25: Added to Savings | M25: =SUMIF(D5:D255,"Added to Savings",F5:F255)
A26: =IF(F26<>"",ROW()-4,"") | L26: CC Payments | M26: =SUMIF(D5:D255,"Credit Card Payment",F5:F255)
A27: =IF(F27<>"",ROW()-4,"") | L27: Miscellaneous | M27: =SUMIF(D5:D255,"Miscellaneous",F5:F255)
A28: =IF(F28<>"",ROW()-4,"")
A29: =IF(F29<>"",ROW()-4,"")
A30: =IF(F30<>"",ROW()-4,"")
A31: =IF(F31<>"",ROW()-4,"")
A32: =IF(F32<>"",ROW()-4,"")
A33: =IF(F33<>"",ROW()-4,"")
A34: =IF(F34<>"",ROW()-4,"")
A35: =IF(F35<>"",ROW()-4,"")
A36: =IF(F36<>"",ROW()-4,"")
A37: =IF(F37<>"",ROW()-4,"")
A38: =IF(F38<>"",ROW()-4,"")
A39: =IF(F39<>"",ROW()-4,"")
... A255: =IF(F255<>"",ROW()-4,"")
A256: TOTAL EXPENSES THIS MONTH | F256: =SUM(F5:F255)

Sheet January
A1: 📝 JANUARY — EXPENSE LOG
A2: ℹ️ Date is DateTime. Category dropdown → Sub-category changes automatically. 'Added to Savings' → pick your saving account in Sub-category. CC spend → pick card in 'CC Name'. CC payment → increases card limit.
A4: # | B4: Date & Time | C4: Description | D4: Category | E4: Sub-category | F4: Amount (₹) | G4: Paid From | H4: CC Name | I4: Account | J4: Notes | L4: 📊 January Summary | M4: Amount (₹)
A5: =IF(F5<>"",ROW()-4,"") | L5: Total Expenses | M5: =F256
A6: =IF(F6<>"",ROW()-4,"") | L6: Income This Month | M6: =Income!E13
A7: =IF(F7<>"",ROW()-4,"") | L7: Net This Month | M7: =M6-M5
A8: =IF(F8<>"",ROW()-4,"") | L8: Savings 1 (this month) | M8: =IF(Setup!A13<>"",SUMIFS(F5:F255,D5:D255,"Added to Savings",I5:I255,Setup!A13)-SUMIFS(F5:F255,G5:G255,Setup!A13),"")
A9: =IF(F9<>"",ROW()-4,"") | L9: Savings 1 (balance) | M9: =IF(Setup!A13<>"",Setup!B13+(SUMIFS('April'!F5:F64,'April'!D5:D64,"Added to Savings",'April'!I5:I64,Setup!A13)+SUMIFS('May'!F5:F64,'May'!D5:D64,"Added to Savings",'May'!I5:I64,Setup!A13)+SUMIFS('June'!F5:F64,'June'!D5:D64,"Added to Savings",'June'!I5:I64,Setup!A13)+SUMIFS('July'!F5:F64,'July'!D5:D64,"Added to Savings",'July'!I5:I64,Setup!A13)+SUMIFS('August'!F5:F64,'August'!D5:D64,"Added to Savings",'August'!I5:I64,Setup!A13)+SUMIFS('September'!F5:F64,'September'!D5:D64,"Added to Savings",'September'!I5:I64,Setup!A13)+SUMIFS('October'!F5:F64,'October'!D5:D64,"Added to Savings",'October'!I5:I64,Setup!A13)+SUMIFS('November'!F5:F64,'November'!D5:D64,"Added to Savings",'November'!I5:I64,Setup!A13)+SUMIFS('December'!F5:F64,'December'!D5:D64,"Added to Savings",'December'!I5:I64,Setup!A13)+SUMIFS('January'!F5:F64,'January'!D5:D64,"Added to Savings",'January'!I5:I64,Setup!A13))-(SUMIFS('April'!F5:F64,'April'!G5:G64,Setup!A13)+SUMIFS('May'!F5:F64,'May'!G5:G64,Setup!A13)+SUMIFS('June'!F5:F64,'June'!G5:G64,Setup!A13)+SUMIFS('July'!F5:F64,'July'!G5:G64,Setup!A13)+SUMIFS('August'!F5:F64,'August'!G5:G64,Setup!A13)+SUMIFS('September'!F5:F64,'September'!G5:G64,Setup!A13)+SUMIFS('October'!F5:F64,'October'!G5:G64,Setup!A13)+SUMIFS('November'!F5:F64,'November'!G5:G64,Setup!A13)+SUMIFS('December'!F5:F64,'December'!G5:G64,Setup!A13)+SUMIFS('January'!F5:F64,'January'!G5:G64,Setup!A13)),"")
A10: =IF(F10<>"",ROW()-4,"") | L10: Savings 2 (this month) | M10: =IF(Setup!A14<>"",SUMIFS(F5:F255,D5:D255,"Added to Savings",I5:I255,Setup!A14)-SUMIFS(F5:F255,G5:G255,Setup!A14),"")
A11: =IF(F11<>"",ROW()-4,"") | L11: Savings 2 (balance) | M11: =IF(Setup!A14<>"",Setup!B14+(SUMIFS('April'!F5:F64,'April'!D5:D64,"Added to Savings",'April'!I5:I64,Setup!A14)+SUMIFS('May'!F5:F64,'May'!D5:D64,"Added to Savings",'May'!I5:I64,Setup!A14)+SUMIFS('June'!F5:F64,'June'!D5:D64,"Added to Savings",'June'!I5:I64,Setup!A14)+SUMIFS('July'!F5:F64,'July'!D5:D64,"Added to Savings",'July'!I5:I64,Setup!A14)+SUMIFS('August'!F5:F64,'August'!D5:D64,"Added to Savings",'August'!I5:I64,Setup!A14)+SUMIFS('September'!F5:F64,'September'!D5:D64,"Added to Savings",'September'!I5:I64,Setup!A14)+SUMIFS('October'!F5:F64,'October'!D5:D64,"Added to Savings",'October'!I5:I64,Setup!A14)+SUMIFS('November'!F5:F64,'November'!D5:D64,"Added to Savings",'November'!I5:I64,Setup!A14)+SUMIFS('December'!F5:F64,'December'!D5:D64,"Added to Savings",'December'!I5:I64,Setup!A14)+SUMIFS('January'!F5:F64,'January'!D5:D64,"Added to Savings",'January'!I5:I64,Setup!A14))-(SUMIFS('April'!F5:F64,'April'!G5:G64,Setup!A14)+SUMIFS('May'!F5:F64,'May'!G5:G64,Setup!A14)+SUMIFS('June'!F5:F64,'June'!G5:G64,Setup!A14)+SUMIFS('July'!F5:F64,'July'!G5:G64,Setup!A14)+SUMIFS('August'!F5:F64,'August'!G5:G64,Setup!A14)+SUMIFS('September'!F5:F64,'September'!G5:G64,Setup!A14)+SUMIFS('October'!F5:F64,'October'!G5:G64,Setup!A14)+SUMIFS('November'!F5:F64,'November'!G5:G64,Setup!A14)+SUMIFS('December'!F5:F64,'December'!G5:G64,Setup!A14)+SUMIFS('January'!F5:F64,'January'!G5:G64,Setup!A14)),"")
A12: =IF(F12<>"",ROW()-4,"") | L12: Savings 3 (this month) | M12: =IF(Setup!A15<>"",SUMIFS(F5:F255,D5:D255,"Added to Savings",I5:I255,Setup!A15)-SUMIFS(F5:F255,G5:G255,Setup!A15),"")
A13: =IF(F13<>"",ROW()-4,"") | L13: Savings 3 (balance) | M13: =IF(Setup!A15<>"",Setup!B15+(SUMIFS('April'!F5:F64,'April'!D5:D64,"Added to Savings",'April'!I5:I64,Setup!A15)+SUMIFS('May'!F5:F64,'May'!D5:D64,"Added to Savings",'May'!I5:I64,Setup!A15)+SUMIFS('June'!F5:F64,'June'!D5:D64,"Added to Savings",'June'!I5:I64,Setup!A15)+SUMIFS('July'!F5:F64,'July'!D5:D64,"Added to Savings",'July'!I5:I64,Setup!A15)+SUMIFS('August'!F5:F64,'August'!D5:D64,"Added to Savings",'August'!I5:I64,Setup!A15)+SUMIFS('September'!F5:F64,'September'!D5:D64,"Added to Savings",'September'!I5:I64,Setup!A15)+SUMIFS('October'!F5:F64,'October'!D5:D64,"Added to Savings",'October'!I5:I64,Setup!A15)+SUMIFS('November'!F5:F64,'November'!D5:D64,"Added to Savings",'November'!I5:I64,Setup!A15)+SUMIFS('December'!F5:F64,'December'!D5:D64,"Added to Savings",'December'!I5:I64,Setup!A15)+SUMIFS('January'!F5:F64,'January'!D5:D64,"Added to Savings",'January'!I5:I64,Setup!A15))-(SUMIFS('April'!F5:F64,'April'!G5:G64,Setup!A15)+SUMIFS('May'!F5:F64,'May'!G5:G64,Setup!A15)+SUMIFS('June'!F5:F64,'June'!G5:G64,Setup!A15)+SUMIFS('July'!F5:F64,'July'!G5:G64,Setup!A15)+SUMIFS('August'!F5:F64,'August'!G5:G64,Setup!A15)+SUMIFS('September'!F5:F64,'September'!G5:G64,Setup!A15)+SUMIFS('October'!F5:F64,'October'!G5:G64,Setup!A15)+SUMIFS('November'!F5:F64,'November'!G5:G64,Setup!A15)+SUMIFS('December'!F5:F64,'December'!G5:G64,Setup!A15)+SUMIFS('January'!F5:F64,'January'!G5:G64,Setup!A15)),"")
A14: =IF(F14<>"",ROW()-4,"") | L14: Savings 4 (this month) | M14: =IF(Setup!A16<>"",SUMIFS(F5:F255,D5:D255,"Added to Savings",I5:I255,Setup!A16)-SUMIFS(F5:F255,G5:G255,Setup!A16),"")
A15: =IF(F15<>"",ROW()-4,"") | L15: Savings 4 (balance) | M15: =IF(Setup!A16<>"",Setup!B16+(SUMIFS('April'!F5:F64,'April'!D5:D64,"Added to Savings",'April'!I5:I64,Setup!A16)+SUMIFS('May'!F5:F64,'May'!D5:D64,"Added to Savings",'May'!I5:I64,Setup!A16)+SUMIFS('June'!F5:F64,'June'!D5:D64,"Added to Savings",'June'!I5:I64,Setup!A16)+SUMIFS('July'!F5:F64,'July'!D5:D64,"Added to Savings",'July'!I5:I64,Setup!A16)+SUMIFS('August'!F5:F64,'August'!D5:D64,"Added to Savings",'August'!I5:I64,Setup!A16)+SUMIFS('September'!F5:F64,'September'!D5:D64,"Added to Savings",'September'!I5:I64,Setup!A16)+SUMIFS('October'!F5:F64,'October'!D5:D64,"Added to Savings",'October'!I5:I64,Setup!A16)+SUMIFS('November'!F5:F64,'November'!D5:D64,"Added to Savings",'November'!I5:I64,Setup!A16)+SUMIFS('December'!F5:F64,'December'!D5:D64,"Added to Savings",'December'!I5:I64,Setup!A16)+SUMIFS('January'!F5:F64,'January'!D5:D64,"Added to Savings",'January'!I5:I64,Setup!A16))-(SUMIFS('April'!F5:F64,'April'!G5:G64,Setup!A16)+SUMIFS('May'!F5:F64,'May'!G5:G64,Setup!A16)+SUMIFS('June'!F5:F64,'June'!G5:G64,Setup!A16)+SUMIFS('July'!F5:F64,'July'!G5:G64,Setup!A16)+SUMIFS('August'!F5:F64,'August'!G5:G64,Setup!A16)+SUMIFS('September'!F5:F64,'September'!G5:G64,Setup!A16)+SUMIFS('October'!F5:F64,'October'!G5:G64,Setup!A16)+SUMIFS('November'!F5:F64,'November'!G5:G64,Setup!A16)+SUMIFS('December'!F5:F64,'December'!G5:G64,Setup!A16)+SUMIFS('January'!F5:F64,'January'!G5:G64,Setup!A16)),"")
A16: =IF(F16<>"",ROW()-4,"") | L16: Savings 5 (this month) | M16: =IF(Setup!A17<>"",SUMIFS(F5:F255,D5:D255,"Added to Savings",I5:I255,Setup!A17)-SUMIFS(F5:F255,G5:G255,Setup!A17),"")
A17: =IF(F17<>"",ROW()-4,"") | L17: Savings 5 (balance) | M17: =IF(Setup!A17<>"",Setup!B17+(SUMIFS('April'!F5:F64,'April'!D5:D64,"Added to Savings",'April'!I5:I64,Setup!A17)+SUMIFS('May'!F5:F64,'May'!D5:D64,"Added to Savings",'May'!I5:I64,Setup!A17)+SUMIFS('June'!F5:F64,'June'!D5:D64,"Added to Savings",'June'!I5:I64,Setup!A17)+SUMIFS('July'!F5:F64,'July'!D5:D64,"Added to Savings",'July'!I5:I64,Setup!A17)+SUMIFS('August'!F5:F64,'August'!D5:D64,"Added to Savings",'August'!I5:I64,Setup!A17)+SUMIFS('September'!F5:F64,'September'!D5:D64,"Added to Savings",'September'!I5:I64,Setup!A17)+SUMIFS('October'!F5:F64,'October'!D5:D64,"Added to Savings",'October'!I5:I64,Setup!A17)+SUMIFS('November'!F5:F64,'November'!D5:D64,"Added to Savings",'November'!I5:I64,Setup!A17)+SUMIFS('December'!F5:F64,'December'!D5:D64,"Added to Savings",'December'!I5:I64,Setup!A17)+SUMIFS('January'!F5:F64,'January'!D5:D64,"Added to Savings",'January'!I5:I64,Setup!A17))-(SUMIFS('April'!F5:F64,'April'!G5:G64,Setup!A17)+SUMIFS('May'!F5:F64,'May'!G5:G64,Setup!A17)+SUMIFS('June'!F5:F64,'June'!G5:G64,Setup!A17)+SUMIFS('July'!F5:F64,'July'!G5:G64,Setup!A17)+SUMIFS('August'!F5:F64,'August'!G5:G64,Setup!A17)+SUMIFS('September'!F5:F64,'September'!G5:G64,Setup!A17)+SUMIFS('October'!F5:F64,'October'!G5:G64,Setup!A17)+SUMIFS('November'!F5:F64,'November'!G5:G64,Setup!A17)+SUMIFS('December'!F5:F64,'December'!G5:G64,Setup!A17)+SUMIFS('January'!F5:F64,'January'!G5:G64,Setup!A17)),"")
A18: =IF(F18<>"",ROW()-4,"") | L18: Fixed Bills Paid | M18: =SUMIF(D5:D255,"Fixed Bills",F5:F255)
A19: =IF(F19<>"",ROW()-4,"") | L19: Food & Dining | M19: =SUMIF(D5:D255,"Food & Dining",F5:F255)
A20: =IF(F20<>"",ROW()-4,"") | L20: Transport | M20: =SUMIF(D5:D255,"Transport & Fuel",F5:F255)
A21: =IF(F21<>"",ROW()-4,"") | L21: Groceries | M21: =SUMIF(D5:D255,"Groceries",F5:F255)
A22: =IF(F22<>"",ROW()-4,"") | L22: Shopping | M22: =SUMIF(D5:D255,"Shopping & Clothing",F5:F255)
A23: =IF(F23<>"",ROW()-4,"") | L23: Entertainment | M23: =SUMIF(D5:D255,"Entertainment & OTT",F5:F255)
A24: =IF(F24<>"",ROW()-4,"") | L24: Investment | M24: =SUMIF(D5:D255,"Investment",F5:F255)
A25: =IF(F25<>"",ROW()-4,"") | L25: Added to Savings | M25: =SUMIF(D5:D255,"Added to Savings",F5:F255)
A26: =IF(F26<>"",ROW()-4,"") | L26: CC Payments | M26: =SUMIF(D5:D255,"Credit Card Payment",F5:F255)
A27: =IF(F27<>"",ROW()-4,"") | L27: Miscellaneous | M27: =SUMIF(D5:D255,"Miscellaneous",F5:F255)
A28: =IF(F28<>"",ROW()-4,"")
A29: =IF(F29<>"",ROW()-4,"")
A30: =IF(F30<>"",ROW()-4,"")
A31: =IF(F31<>"",ROW()-4,"")
A32: =IF(F32<>"",ROW()-4,"")
A33: =IF(F33<>"",ROW()-4,"")
A34: =IF(F34<>"",ROW()-4,"")
A35: =IF(F35<>"",ROW()-4,"")
A36: =IF(F36<>"",ROW()-4,"")
A37: =IF(F37<>"",ROW()-4,"")
A38: =IF(F38<>"",ROW()-4,"")
A39: =IF(F39<>"",ROW()-4,"")
... A255: =IF(F255<>"",ROW()-4,"")
A256: TOTAL EXPENSES THIS MONTH | F256: =SUM(F5:F255)

Sheet February
A1: 📝 FEBRUARY — EXPENSE LOG
A2: ℹ️ Date is DateTime. Category dropdown → Sub-category changes automatically. 'Added to Savings' → pick your saving account in Sub-category. CC spend → pick card in 'CC Name'. CC payment → increases card limit.
A4: # | B4: Date & Time | C4: Description | D4: Category | E4: Sub-category | F4: Amount (₹) | G4: Paid From | H4: CC Name | I4: Account | J4: Notes | L4: 📊 February Summary | M4: Amount (₹)
A5: =IF(F5<>"",ROW()-4,"") | L5: Total Expenses | M5: =F256
A6: =IF(F6<>"",ROW()-4,"") | L6: Income This Month | M6: =Income!E14
A7: =IF(F7<>"",ROW()-4,"") | L7: Net This Month | M7: =M6-M5
A8: =IF(F8<>"",ROW()-4,"") | L8: Savings 1 (this month) | M8: =IF(Setup!A13<>"",SUMIFS(F5:F255,D5:D255,"Added to Savings",I5:I255,Setup!A13)-SUMIFS(F5:F255,G5:G255,Setup!A13),"")
A9: =IF(F9<>"",ROW()-4,"") | L9: Savings 1 (balance) | M9: =IF(Setup!A13<>"",Setup!B13+(SUMIFS('April'!F5:F64,'April'!D5:D64,"Added to Savings",'April'!I5:I64,Setup!A13)+SUMIFS('May'!F5:F64,'May'!D5:D64,"Added to Savings",'May'!I5:I64,Setup!A13)+SUMIFS('June'!F5:F64,'June'!D5:D64,"Added to Savings",'June'!I5:I64,Setup!A13)+SUMIFS('July'!F5:F64,'July'!D5:D64,"Added to Savings",'July'!I5:I64,Setup!A13)+SUMIFS('August'!F5:F64,'August'!D5:D64,"Added to Savings",'August'!I5:I64,Setup!A13)+SUMIFS('September'!F5:F64,'September'!D5:D64,"Added to Savings",'September'!I5:I64,Setup!A13)+SUMIFS('October'!F5:F64,'October'!D5:D64,"Added to Savings",'October'!I5:I64,Setup!A13)+SUMIFS('November'!F5:F64,'November'!D5:D64,"Added to Savings",'November'!I5:I64,Setup!A13)+SUMIFS('December'!F5:F64,'December'!D5:D64,"Added to Savings",'December'!I5:I64,Setup!A13)+SUMIFS('January'!F5:F64,'January'!D5:D64,"Added to Savings",'January'!I5:I64,Setup!A13)+SUMIFS('February'!F5:F64,'February'!D5:D64,"Added to Savings",'February'!I5:I64,Setup!A13))-(SUMIFS('April'!F5:F64,'April'!G5:G64,Setup!A13)+SUMIFS('May'!F5:F64,'May'!G5:G64,Setup!A13)+SUMIFS('June'!F5:F64,'June'!G5:G64,Setup!A13)+SUMIFS('July'!F5:F64,'July'!G5:G64,Setup!A13)+SUMIFS('August'!F5:F64,'August'!G5:G64,Setup!A13)+SUMIFS('September'!F5:F64,'September'!G5:G64,Setup!A13)+SUMIFS('October'!F5:F64,'October'!G5:G64,Setup!A13)+SUMIFS('November'!F5:F64,'November'!G5:G64,Setup!A13)+SUMIFS('December'!F5:F64,'December'!G5:G64,Setup!A13)+SUMIFS('January'!F5:F64,'January'!G5:G64,Setup!A13)+SUMIFS('February'!F5:F64,'February'!G5:G64,Setup!A13)),"")
A10: =IF(F10<>"",ROW()-4,"") | L10: Savings 2 (this month) | M10: =IF(Setup!A14<>"",SUMIFS(F5:F255,D5:D255,"Added to Savings",I5:I255,Setup!A14)-SUMIFS(F5:F255,G5:G255,Setup!A14),"")
A11: =IF(F11<>"",ROW()-4,"") | L11: Savings 2 (balance) | M11: =IF(Setup!A14<>"",Setup!B14+(SUMIFS('April'!F5:F64,'April'!D5:D64,"Added to Savings",'April'!I5:I64,Setup!A14)+SUMIFS('May'!F5:F64,'May'!D5:D64,"Added to Savings",'May'!I5:I64,Setup!A14)+SUMIFS('June'!F5:F64,'June'!D5:D64,"Added to Savings",'June'!I5:I64,Setup!A14)+SUMIFS('July'!F5:F64,'July'!D5:D64,"Added to Savings",'July'!I5:I64,Setup!A14)+SUMIFS('August'!F5:F64,'August'!D5:D64,"Added to Savings",'August'!I5:I64,Setup!A14)+SUMIFS('September'!F5:F64,'September'!D5:D64,"Added to Savings",'September'!I5:I64,Setup!A14)+SUMIFS('October'!F5:F64,'October'!D5:D64,"Added to Savings",'October'!I5:I64,Setup!A14)+SUMIFS('November'!F5:F64,'November'!D5:D64,"Added to Savings",'November'!I5:I64,Setup!A14)+SUMIFS('December'!F5:F64,'December'!D5:D64,"Added to Savings",'December'!I5:I64,Setup!A14)+SUMIFS('January'!F5:F64,'January'!D5:D64,"Added to Savings",'January'!I5:I64,Setup!A14)+SUMIFS('February'!F5:F64,'February'!D5:D64,"Added to Savings",'February'!I5:I64,Setup!A14))-(SUMIFS('April'!F5:F64,'April'!G5:G64,Setup!A14)+SUMIFS('May'!F5:F64,'May'!G5:G64,Setup!A14)+SUMIFS('June'!F5:F64,'June'!G5:G64,Setup!A14)+SUMIFS('July'!F5:F64,'July'!G5:G64,Setup!A14)+SUMIFS('August'!F5:F64,'August'!G5:G64,Setup!A14)+SUMIFS('September'!F5:F64,'September'!G5:G64,Setup!A14)+SUMIFS('October'!F5:F64,'October'!G5:G64,Setup!A14)+SUMIFS('November'!F5:F64,'November'!G5:G64,Setup!A14)+SUMIFS('December'!F5:F64,'December'!G5:G64,Setup!A14)+SUMIFS('January'!F5:F64,'January'!G5:G64,Setup!A14)+SUMIFS('February'!F5:F64,'February'!G5:G64,Setup!A14)),"")
A12: =IF(F12<>"",ROW()-4,"") | L12: Savings 3 (this month) | M12: =IF(Setup!A15<>"",SUMIFS(F5:F255,D5:D255,"Added to Savings",I5:I255,Setup!A15)-SUMIFS(F5:F255,G5:G255,Setup!A15),"")
A13: =IF(F13<>"",ROW()-4,"") | L13: Savings 3 (balance) | M13: =IF(Setup!A15<>"",Setup!B15+(SUMIFS('April'!F5:F64,'April'!D5:D64,"Added to Savings",'April'!I5:I64,Setup!A15)+SUMIFS('May'!F5:F64,'May'!D5:D64,"Added to Savings",'May'!I5:I64,Setup!A15)+SUMIFS('June'!F5:F64,'June'!D5:D64,"Added to Savings",'June'!I5:I64,Setup!A15)+SUMIFS('July'!F5:F64,'July'!D5:D64,"Added to Savings",'July'!I5:I64,Setup!A15)+SUMIFS('August'!F5:F64,'August'!D5:D64,"Added to Savings",'August'!I5:I64,Setup!A15)+SUMIFS('September'!F5:F64,'September'!D5:D64,"Added to Savings",'September'!I5:I64,Setup!A15)+SUMIFS('October'!F5:F64,'October'!D5:D64,"Added to Savings",'October'!I5:I64,Setup!A15)+SUMIFS('November'!F5:F64,'November'!D5:D64,"Added to Savings",'November'!I5:I64,Setup!A15)+SUMIFS('December'!F5:F64,'December'!D5:D64,"Added to Savings",'December'!I5:I64,Setup!A15)+SUMIFS('January'!F5:F64,'January'!D5:D64,"Added to Savings",'January'!I5:I64,Setup!A15)+SUMIFS('February'!F5:F64,'February'!D5:D64,"Added to Savings",'February'!I5:I64,Setup!A15))-(SUMIFS('April'!F5:F64,'April'!G5:G64,Setup!A15)+SUMIFS('May'!F5:F64,'May'!G5:G64,Setup!A15)+SUMIFS('June'!F5:F64,'June'!G5:G64,Setup!A15)+SUMIFS('July'!F5:F64,'July'!G5:G64,Setup!A15)+SUMIFS('August'!F5:F64,'August'!G5:G64,Setup!A15)+SUMIFS('September'!F5:F64,'September'!G5:G64,Setup!A15)+SUMIFS('October'!F5:F64,'October'!G5:G64,Setup!A15)+SUMIFS('November'!F5:F64,'November'!G5:G64,Setup!A15)+SUMIFS('December'!F5:F64,'December'!G5:G64,Setup!A15)+SUMIFS('January'!F5:F64,'January'!G5:G64,Setup!A15)+SUMIFS('February'!F5:F64,'February'!G5:G64,Setup!A15)),"")
A14: =IF(F14<>"",ROW()-4,"") | L14: Savings 4 (this month) | M14: =IF(Setup!A16<>"",SUMIFS(F5:F255,D5:D255,"Added to Savings",I5:I255,Setup!A16)-SUMIFS(F5:F255,G5:G255,Setup!A16),"")
A15: =IF(F15<>"",ROW()-4,"") | L15: Savings 4 (balance) | M15: =IF(Setup!A16<>"",Setup!B16+(SUMIFS('April'!F5:F64,'April'!D5:D64,"Added to Savings",'April'!I5:I64,Setup!A16)+SUMIFS('May'!F5:F64,'May'!D5:D64,"Added to Savings",'May'!I5:I64,Setup!A16)+SUMIFS('June'!F5:F64,'June'!D5:D64,"Added to Savings",'June'!I5:I64,Setup!A16)+SUMIFS('July'!F5:F64,'July'!D5:D64,"Added to Savings",'July'!I5:I64,Setup!A16)+SUMIFS('August'!F5:F64,'August'!D5:D64,"Added to Savings",'August'!I5:I64,Setup!A16)+SUMIFS('September'!F5:F64,'September'!D5:D64,"Added to Savings",'September'!I5:I64,Setup!A16)+SUMIFS('October'!F5:F64,'October'!D5:D64,"Added to Savings",'October'!I5:I64,Setup!A16)+SUMIFS('November'!F5:F64,'November'!D5:D64,"Added to Savings",'November'!I5:I64,Setup!A16)+SUMIFS('December'!F5:F64,'December'!D5:D64,"Added to Savings",'December'!I5:I64,Setup!A16)+SUMIFS('January'!F5:F64,'January'!D5:D64,"Added to Savings",'January'!I5:I64,Setup!A16)+SUMIFS('February'!F5:F64,'February'!D5:D64,"Added to Savings",'February'!I5:I64,Setup!A16))-(SUMIFS('April'!F5:F64,'April'!G5:G64,Setup!A16)+SUMIFS('May'!F5:F64,'May'!G5:G64,Setup!A16)+SUMIFS('June'!F5:F64,'June'!G5:G64,Setup!A16)+SUMIFS('July'!F5:F64,'July'!G5:G64,Setup!A16)+SUMIFS('August'!F5:F64,'August'!G5:G64,Setup!A16)+SUMIFS('September'!F5:F64,'September'!G5:G64,Setup!A16)+SUMIFS('October'!F5:F64,'October'!G5:G64,Setup!A16)+SUMIFS('November'!F5:F64,'November'!G5:G64,Setup!A16)+SUMIFS('December'!F5:F64,'December'!G5:G64,Setup!A16)+SUMIFS('January'!F5:F64,'January'!G5:G64,Setup!A16)+SUMIFS('February'!F5:F64,'February'!G5:G64,Setup!A16)),"")
A16: =IF(F16<>"",ROW()-4,"") | L16: Savings 5 (this month) | M16: =IF(Setup!A17<>"",SUMIFS(F5:F255,D5:D255,"Added to Savings",I5:I255,Setup!A17)-SUMIFS(F5:F255,G5:G255,Setup!A17),"")
A17: =IF(F17<>"",ROW()-4,"") | L17: Savings 5 (balance) | M17: =IF(Setup!A17<>"",Setup!B17+(SUMIFS('April'!F5:F64,'April'!D5:D64,"Added to Savings",'April'!I5:I64,Setup!A17)+SUMIFS('May'!F5:F64,'May'!D5:D64,"Added to Savings",'May'!I5:I64,Setup!A17)+SUMIFS('June'!F5:F64,'June'!D5:D64,"Added to Savings",'June'!I5:I64,Setup!A17)+SUMIFS('July'!F5:F64,'July'!D5:D64,"Added to Savings",'July'!I5:I64,Setup!A17)+SUMIFS('August'!F5:F64,'August'!D5:D64,"Added to Savings",'August'!I5:I64,Setup!A17)+SUMIFS('September'!F5:F64,'September'!D5:D64,"Added to Savings",'September'!I5:I64,Setup!A17)+SUMIFS('October'!F5:F64,'October'!D5:D64,"Added to Savings",'October'!I5:I64,Setup!A17)+SUMIFS('November'!F5:F64,'November'!D5:D64,"Added to Savings",'November'!I5:I64,Setup!A17)+SUMIFS('December'!F5:F64,'December'!D5:D64,"Added to Savings",'December'!I5:I64,Setup!A17)+SUMIFS('January'!F5:F64,'January'!D5:D64,"Added to Savings",'January'!I5:I64,Setup!A17)+SUMIFS('February'!F5:F64,'February'!D5:D64,"Added to Savings",'February'!I5:I64,Setup!A17))-(SUMIFS('April'!F5:F64,'April'!G5:G64,Setup!A17)+SUMIFS('May'!F5:F64,'May'!G5:G64,Setup!A17)+SUMIFS('June'!F5:F64,'June'!G5:G64,Setup!A17)+SUMIFS('July'!F5:F64,'July'!G5:G64,Setup!A17)+SUMIFS('August'!F5:F64,'August'!G5:G64,Setup!A17)+SUMIFS('September'!F5:F64,'September'!G5:G64,Setup!A17)+SUMIFS('October'!F5:F64,'October'!G5:G64,Setup!A17)+SUMIFS('November'!F5:F64,'November'!G5:G64,Setup!A17)+SUMIFS('December'!F5:F64,'December'!G5:G64,Setup!A17)+SUMIFS('January'!F5:F64,'January'!G5:G64,Setup!A17)+SUMIFS('February'!F5:F64,'February'!G5:G64,Setup!A17)),"")
A18: =IF(F18<>"",ROW()-4,"") | L18: Fixed Bills Paid | M18: =SUMIF(D5:D255,"Fixed Bills",F5:F255)
A19: =IF(F19<>"",ROW()-4,"") | L19: Food & Dining | M19: =SUMIF(D5:D255,"Food & Dining",F5:F255)
A20: =IF(F20<>"",ROW()-4,"") | L20: Transport | M20: =SUMIF(D5:D255,"Transport & Fuel",F5:F255)
A21: =IF(F21<>"",ROW()-4,"") | L21: Groceries | M21: =SUMIF(D5:D255,"Groceries",F5:F255)
A22: =IF(F22<>"",ROW()-4,"") | L22: Shopping | M22: =SUMIF(D5:D255,"Shopping & Clothing",F5:F255)
A23: =IF(F23<>"",ROW()-4,"") | L23: Entertainment | M23: =SUMIF(D5:D255,"Entertainment & OTT",F5:F255)
A24: =IF(F24<>"",ROW()-4,"") | L24: Investment | M24: =SUMIF(D5:D255,"Investment",F5:F255)
A25: =IF(F25<>"",ROW()-4,"") | L25: Added to Savings | M25: =SUMIF(D5:D255,"Added to Savings",F5:F255)
A26: =IF(F26<>"",ROW()-4,"") | L26: CC Payments | M26: =SUMIF(D5:D255,"Credit Card Payment",F5:F255)
A27: =IF(F27<>"",ROW()-4,"") | L27: Miscellaneous | M27: =SUMIF(D5:D255,"Miscellaneous",F5:F255)
A28: =IF(F28<>"",ROW()-4,"")
A29: =IF(F29<>"",ROW()-4,"")
A30: =IF(F30<>"",ROW()-4,"")
A31: =IF(F31<>"",ROW()-4,"")
A32: =IF(F32<>"",ROW()-4,"")
A33: =IF(F33<>"",ROW()-4,"")
A34: =IF(F34<>"",ROW()-4,"")
A35: =IF(F35<>"",ROW()-4,"")
A36: =IF(F36<>"",ROW()-4,"")
A37: =IF(F37<>"",ROW()-4,"")
A38: =IF(F38<>"",ROW()-4,"")
A39: =IF(F39<>"",ROW()-4,"")
... A255: =IF(F255<>"",ROW()-4,"")
A256: TOTAL EXPENSES THIS MONTH | F256: =SUM(F5:F255)

Sheet March
A1: 📝 MARCH — EXPENSE LOG
A2: ℹ️ Date is DateTime. Category dropdown → Sub-category changes automatically. 'Added to Savings' → pick your saving account in Sub-category. CC spend → pick card in 'CC Name'. CC payment → increases card limit.
A4: # | B4: Date & Time | C4: Description | D4: Category | E4: Sub-category | F4: Amount (₹) | G4: Paid From | H4: CC Name | I4: Account | J4: Notes | L4: 📊 March Summary | M4: Amount (₹)
A5: =IF(F5<>"",ROW()-4,"") | L5: Total Expenses | M5: =F256
A6: =IF(F6<>"",ROW()-4,"") | L6: Income This Month | M6: =Income!E15
A7: =IF(F7<>"",ROW()-4,"") | L7: Net This Month | M7: =M6-M5
A8: =IF(F8<>"",ROW()-4,"") | L8: Savings 1 (this month) | M8: =IF(Setup!A13<>"",SUMIFS(F5:F255,D5:D255,"Added to Savings",I5:I255,Setup!A13)-SUMIFS(F5:F255,G5:G255,Setup!A13),"")
A9: =IF(F9<>"",ROW()-4,"") | L9: Savings 1 (balance) | M9: =IF(Setup!A13<>"",Setup!B13+(SUMIFS('April'!F5:F64,'April'!D5:D64,"Added to Savings",'April'!I5:I64,Setup!A13)+SUMIFS('May'!F5:F64,'May'!D5:D64,"Added to Savings",'May'!I5:I64,Setup!A13)+SUMIFS('June'!F5:F64,'June'!D5:D64,"Added to Savings",'June'!I5:I64,Setup!A13)+SUMIFS('July'!F5:F64,'July'!D5:D64,"Added to Savings",'July'!I5:I64,Setup!A13)+SUMIFS('August'!F5:F64,'August'!D5:D64,"Added to Savings",'August'!I5:I64,Setup!A13)+SUMIFS('September'!F5:F64,'September'!D5:D64,"Added to Savings",'September'!I5:I64,Setup!A13)+SUMIFS('October'!F5:F64,'October'!D5:D64,"Added to Savings",'October'!I5:I64,Setup!A13)+SUMIFS('November'!F5:F64,'November'!D5:D64,"Added to Savings",'November'!I5:I64,Setup!A13)+SUMIFS('December'!F5:F64,'December'!D5:D64,"Added to Savings",'December'!I5:I64,Setup!A13)+SUMIFS('January'!F5:F64,'January'!D5:D64,"Added to Savings",'January'!I5:I64,Setup!A13)+SUMIFS('February'!F5:F64,'February'!D5:D64,"Added to Savings",'February'!I5:I64,Setup!A13)+SUMIFS('March'!F5:F64,'March'!D5:D64,"Added to Savings",'March'!I5:I64,Setup!A13))-(SUMIFS('April'!F5:F64,'April'!G5:G64,Setup!A13)+SUMIFS('May'!F5:F64,'May'!G5:G64,Setup!A13)+SUMIFS('June'!F5:F64,'June'!G5:G64,Setup!A13)+SUMIFS('July'!F5:F64,'July'!G5:G64,Setup!A13)+SUMIFS('August'!F5:F64,'August'!G5:G64,Setup!A13)+SUMIFS('September'!F5:F64,'September'!G5:G64,Setup!A13)+SUMIFS('October'!F5:F64,'October'!G5:G64,Setup!A13)+SUMIFS('November'!F5:F64,'November'!G5:G64,Setup!A13)+SUMIFS('December'!F5:F64,'December'!G5:G64,Setup!A13)+SUMIFS('January'!F5:F64,'January'!G5:G64,Setup!A13)+SUMIFS('February'!F5:F64,'February'!G5:G64,Setup!A13)+SUMIFS('March'!F5:F64,'March'!G5:G64,Setup!A13)),"")
A10: =IF(F10<>"",ROW()-4,"") | L10: Savings 2 (this month) | M10: =IF(Setup!A14<>"",SUMIFS(F5:F255,D5:D255,"Added to Savings",I5:I255,Setup!A14)-SUMIFS(F5:F255,G5:G255,Setup!A14),"")
A11: =IF(F11<>"",ROW()-4,"") | L11: Savings 2 (balance) | M11: =IF(Setup!A14<>"",Setup!B14+(SUMIFS('April'!F5:F64,'April'!D5:D64,"Added to Savings",'April'!I5:I64,Setup!A14)+SUMIFS('May'!F5:F64,'May'!D5:D64,"Added to Savings",'May'!I5:I64,Setup!A14)+SUMIFS('June'!F5:F64,'June'!D5:D64,"Added to Savings",'June'!I5:I64,Setup!A14)+SUMIFS('July'!F5:F64,'July'!D5:D64,"Added to Savings",'July'!I5:I64,Setup!A14)+SUMIFS('August'!F5:F64,'August'!D5:D64,"Added to Savings",'August'!I5:I64,Setup!A14)+SUMIFS('September'!F5:F64,'September'!D5:D64,"Added to Savings",'September'!I5:I64,Setup!A14)+SUMIFS('October'!F5:F64,'October'!D5:D64,"Added to Savings",'October'!I5:I64,Setup!A14)+SUMIFS('November'!F5:F64,'November'!D5:D64,"Added to Savings",'November'!I5:I64,Setup!A14)+SUMIFS('December'!F5:F64,'December'!D5:D64,"Added to Savings",'December'!I5:I64,Setup!A14)+SUMIFS('January'!F5:F64,'January'!D5:D64,"Added to Savings",'January'!I5:I64,Setup!A14)+SUMIFS('February'!F5:F64,'February'!D5:D64,"Added to Savings",'February'!I5:I64,Setup!A14)+SUMIFS('March'!F5:F64,'March'!D5:D64,"Added to Savings",'March'!I5:I64,Setup!A14))-(SUMIFS('April'!F5:F64,'April'!G5:G64,Setup!A14)+SUMIFS('May'!F5:F64,'May'!G5:G64,Setup!A14)+SUMIFS('June'!F5:F64,'June'!G5:G64,Setup!A14)+SUMIFS('July'!F5:F64,'July'!G5:G64,Setup!A14)+SUMIFS('August'!F5:F64,'August'!G5:G64,Setup!A14)+SUMIFS('September'!F5:F64,'September'!G5:G64,Setup!A14)+SUMIFS('October'!F5:F64,'October'!G5:G64,Setup!A14)+SUMIFS('November'!F5:F64,'November'!G5:G64,Setup!A14)+SUMIFS('December'!F5:F64,'December'!G5:G64,Setup!A14)+SUMIFS('January'!F5:F64,'January'!G5:G64,Setup!A14)+SUMIFS('February'!F5:F64,'February'!G5:G64,Setup!A14)+SUMIFS('March'!F5:F64,'March'!G5:G64,Setup!A14)),"")
A12: =IF(F12<>"",ROW()-4,"") | L12: Savings 3 (this month) | M12: =IF(Setup!A15<>"",SUMIFS(F5:F255,D5:D255,"Added to Savings",I5:I255,Setup!A15)-SUMIFS(F5:F255,G5:G255,Setup!A15),"")
A13: =IF(F13<>"",ROW()-4,"") | L13: Savings 3 (balance) | M13: =IF(Setup!A15<>"",Setup!B15+(SUMIFS('April'!F5:F64,'April'!D5:D64,"Added to Savings",'April'!I5:I64,Setup!A15)+SUMIFS('May'!F5:F64,'May'!D5:D64,"Added to Savings",'May'!I5:I64,Setup!A15)+SUMIFS('June'!F5:F64,'June'!D5:D64,"Added to Savings",'June'!I5:I64,Setup!A15)+SUMIFS('July'!F5:F64,'July'!D5:D64,"Added to Savings",'July'!I5:I64,Setup!A15)+SUMIFS('August'!F5:F64,'August'!D5:D64,"Added to Savings",'August'!I5:I64,Setup!A15)+SUMIFS('September'!F5:F64,'September'!D5:D64,"Added to Savings",'September'!I5:I64,Setup!A15)+SUMIFS('October'!F5:F64,'October'!D5:D64,"Added to Savings",'October'!I5:I64,Setup!A15)+SUMIFS('November'!F5:F64,'November'!D5:D64,"Added to Savings",'November'!I5:I64,Setup!A15)+SUMIFS('December'!F5:F64,'December'!D5:D64,"Added to Savings",'December'!I5:I64,Setup!A15)+SUMIFS('January'!F5:F64,'January'!D5:D64,"Added to Savings",'January'!I5:I64,Setup!A15)+SUMIFS('February'!F5:F64,'February'!D5:D64,"Added to Savings",'February'!I5:I64,Setup!A15)+SUMIFS('March'!F5:F64,'March'!D5:D64,"Added to Savings",'March'!I5:I64,Setup!A15))-(SUMIFS('April'!F5:F64,'April'!G5:G64,Setup!A15)+SUMIFS('May'!F5:F64,'May'!G5:G64,Setup!A15)+SUMIFS('June'!F5:F64,'June'!G5:G64,Setup!A15)+SUMIFS('July'!F5:F64,'July'!G5:G64,Setup!A15)+SUMIFS('August'!F5:F64,'August'!G5:G64,Setup!A15)+SUMIFS('September'!F5:F64,'September'!G5:G64,Setup!A15)+SUMIFS('October'!F5:F64,'October'!G5:G64,Setup!A15)+SUMIFS('November'!F5:F64,'November'!G5:G64,Setup!A15)+SUMIFS('December'!F5:F64,'December'!G5:G64,Setup!A15)+SUMIFS('January'!F5:F64,'January'!G5:G64,Setup!A15)+SUMIFS('February'!F5:F64,'February'!G5:G64,Setup!A15)+SUMIFS('March'!F5:F64,'March'!G5:G64,Setup!A15)),"")
A14: =IF(F14<>"",ROW()-4,"") | L14: Savings 4 (this month) | M14: =IF(Setup!A16<>"",SUMIFS(F5:F255,D5:D255,"Added to Savings",I5:I255,Setup!A16)-SUMIFS(F5:F255,G5:G255,Setup!A16),"")
A15: =IF(F15<>"",ROW()-4,"") | L15: Savings 4 (balance) | M15: =IF(Setup!A16<>"",Setup!B16+(SUMIFS('April'!F5:F64,'April'!D5:D64,"Added to Savings",'April'!I5:I64,Setup!A16)+SUMIFS('May'!F5:F64,'May'!D5:D64,"Added to Savings",'May'!I5:I64,Setup!A16)+SUMIFS('June'!F5:F64,'June'!D5:D64,"Added to Savings",'June'!I5:I64,Setup!A16)+SUMIFS('July'!F5:F64,'July'!D5:D64,"Added to Savings",'July'!I5:I64,Setup!A16)+SUMIFS('August'!F5:F64,'August'!D5:D64,"Added to Savings",'August'!I5:I64,Setup!A16)+SUMIFS('September'!F5:F64,'September'!D5:D64,"Added to Savings",'September'!I5:I64,Setup!A16)+SUMIFS('October'!F5:F64,'October'!D5:D64,"Added to Savings",'October'!I5:I64,Setup!A16)+SUMIFS('November'!F5:F64,'November'!D5:D64,"Added to Savings",'November'!I5:I64,Setup!A16)+SUMIFS('December'!F5:F64,'December'!D5:D64,"Added to Savings",'December'!I5:I64,Setup!A16)+SUMIFS('January'!F5:F64,'January'!D5:D64,"Added to Savings",'January'!I5:I64,Setup!A16)+SUMIFS('February'!F5:F64,'February'!D5:D64,"Added to Savings",'February'!I5:I64,Setup!A16)+SUMIFS('March'!F5:F64,'March'!D5:D64,"Added to Savings",'March'!I5:I64,Setup!A16))-(SUMIFS('April'!F5:F64,'April'!G5:G64,Setup!A16)+SUMIFS('May'!F5:F64,'May'!G5:G64,Setup!A16)+SUMIFS('June'!F5:F64,'June'!G5:G64,Setup!A16)+SUMIFS('July'!F5:F64,'July'!G5:G64,Setup!A16)+SUMIFS('August'!F5:F64,'August'!G5:G64,Setup!A16)+SUMIFS('September'!F5:F64,'September'!G5:G64,Setup!A16)+SUMIFS('October'!F5:F64,'October'!G5:G64,Setup!A16)+SUMIFS('November'!F5:F64,'November'!G5:G64,Setup!A16)+SUMIFS('December'!F5:F64,'December'!G5:G64,Setup!A16)+SUMIFS('January'!F5:F64,'January'!G5:G64,Setup!A16)+SUMIFS('February'!F5:F64,'February'!G5:G64,Setup!A16)+SUMIFS('March'!F5:F64,'March'!G5:G64,Setup!A16)),"")
A16: =IF(F16<>"",ROW()-4,"") | L16: Savings 5 (this month) | M16: =IF(Setup!A17<>"",SUMIFS(F5:F255,D5:D255,"Added to Savings",I5:I255,Setup!A17)-SUMIFS(F5:F255,G5:G255,Setup!A17),"")
A17: =IF(F17<>"",ROW()-4,"") | L17: Savings 5 (balance) | M17: =IF(Setup!A17<>"",Setup!B17+(SUMIFS('April'!F5:F64,'April'!D5:D64,"Added to Savings",'April'!I5:I64,Setup!A17)+SUMIFS('May'!F5:F64,'May'!D5:D64,"Added to Savings",'May'!I5:I64,Setup!A17)+SUMIFS('June'!F5:F64,'June'!D5:D64,"Added to Savings",'June'!I5:I64,Setup!A17)+SUMIFS('July'!F5:F64,'July'!D5:D64,"Added to Savings",'July'!I5:I64,Setup!A17)+SUMIFS('August'!F5:F64,'August'!D5:D64,"Added to Savings",'August'!I5:I64,Setup!A17)+SUMIFS('September'!F5:F64,'September'!D5:D64,"Added to Savings",'September'!I5:I64,Setup!A17)+SUMIFS('October'!F5:F64,'October'!D5:D64,"Added to Savings",'October'!I5:I64,Setup!A17)+SUMIFS('November'!F5:F64,'November'!D5:D64,"Added to Savings",'November'!I5:I64,Setup!A17)+SUMIFS('December'!F5:F64,'December'!D5:D64,"Added to Savings",'December'!I5:I64,Setup!A17)+SUMIFS('January'!F5:F64,'January'!D5:D64,"Added to Savings",'January'!I5:I64,Setup!A17)+SUMIFS('February'!F5:F64,'February'!D5:D64,"Added to Savings",'February'!I5:I64,Setup!A17)+SUMIFS('March'!F5:F64,'March'!D5:D64,"Added to Savings",'March'!I5:I64,Setup!A17))-(SUMIFS('April'!F5:F64,'April'!G5:G64,Setup!A17)+SUMIFS('May'!F5:F64,'May'!G5:G64,Setup!A17)+SUMIFS('June'!F5:F64,'June'!G5:G64,Setup!A17)+SUMIFS('July'!F5:F64,'July'!G5:G64,Setup!A17)+SUMIFS('August'!F5:F64,'August'!G5:G64,Setup!A17)+SUMIFS('September'!F5:F64,'September'!G5:G64,Setup!A17)+SUMIFS('October'!F5:F64,'October'!G5:G64,Setup!A17)+SUMIFS('November'!F5:F64,'November'!G5:G64,Setup!A17)+SUMIFS('December'!F5:F64,'December'!G5:G64,Setup!A17)+SUMIFS('January'!F5:F64,'January'!G5:G64,Setup!A17)+SUMIFS('February'!F5:F64,'February'!G5:G64,Setup!A17)+SUMIFS('March'!F5:F64,'March'!G5:G64,Setup!A17)),"")
A18: =IF(F18<>"",ROW()-4,"") | L18: Fixed Bills Paid | M18: =SUMIF(D5:D255,"Fixed Bills",F5:F255)
A19: =IF(F19<>"",ROW()-4,"") | L19: Food & Dining | M19: =SUMIF(D5:D255,"Food & Dining",F5:F255)
A20: =IF(F20<>"",ROW()-4,"") | L20: Transport | M20: =SUMIF(D5:D255,"Transport & Fuel",F5:F255)
A21: =IF(F21<>"",ROW()-4,"") | L21: Groceries | M21: =SUMIF(D5:D255,"Groceries",F5:F255)
A22: =IF(F22<>"",ROW()-4,"") | L22: Shopping | M22: =SUMIF(D5:D255,"Shopping & Clothing",F5:F255)
A23: =IF(F23<>"",ROW()-4,"") | L23: Entertainment | M23: =SUMIF(D5:D255,"Entertainment & OTT",F5:F255)
A24: =IF(F24<>"",ROW()-4,"") | L24: Investment | M24: =SUMIF(D5:D255,"Investment",F5:F255)
A25: =IF(F25<>"",ROW()-4,"") | L25: Added to Savings | M25: =SUMIF(D5:D255,"Added to Savings",F5:F255)
A26: =IF(F26<>"",ROW()-4,"") | L26: CC Payments | M26: =SUMIF(D5:D255,"Credit Card Payment",F5:F255)
A27: =IF(F27<>"",ROW()-4,"") | L27: Miscellaneous | M27: =SUMIF(D5:D255,"Miscellaneous",F5:F255)
A28: =IF(F28<>"",ROW()-4,"")
A29: =IF(F29<>"",ROW()-4,"")
A30: =IF(F30<>"",ROW()-4,"")
A31: =IF(F31<>"",ROW()-4,"")
A32: =IF(F32<>"",ROW()-4,"")
A33: =IF(F33<>"",ROW()-4,"")
A34: =IF(F34<>"",ROW()-4,"")
A35: =IF(F35<>"",ROW()-4,"")
A36: =IF(F36<>"",ROW()-4,"")
A37: =IF(F37<>"",ROW()-4,"")
A38: =IF(F38<>"",ROW()-4,"")
A39: =IF(F39<>"",ROW()-4,"")
... A255: =IF(F255<>"",ROW()-4,"")
A256: TOTAL EXPENSES THIS MONTH | F256: =SUM(F5:F255)

Sheet Credit Cards
A1: 💳 CREDIT CARD TRACKER — Auto-updated from monthly expense sheets
A3: ⚙️ CARD SETUP (edit in Setup sheet)
A4: # | B4: Card Name | C4: Credit Limit (₹) | D4: Opening Dues (₹) | E4: Total Spent (₹) | F4: Total Paid (₹) | G4: Balance Owed (₹) | H4: Available Credit (₹)
A5: 1 | B5: =Setup!D5 | C5: =Setup!E5 | D5: =Setup!F5 | E5: =SUMIF('April'!H:H,B5,'April'!F:F)+SUMIF('May'!H:H,B5,'May'!F:F)+SUMIF('June'!H:H,B5,'June'!F:F)+SUMIF('July'!H:H,B5,'July'!F:F)+SUMIF('August'!H:H,B5,'August'!F:F)+SUMIF('September'!H:H,B5,'September'!F:F)+SUMIF('October'!H:H,B5,'October'!F:F)+SUMIF('November'!H:H,B5,'November'!F:F)+SUMIF('December'!H:H,B5,'December'!F:F)+SUMIF('January'!H:H,B5,'January'!F:F)+SUMIF('February'!H:H,B5,'February'!F:F)+SUMIF('March'!H:H,B5,'March'!F:F) | F5: =SUMIFS('April'!F:F,'April'!D:D,"Credit Card Payment",'April'!I:I,B5)+SUMIFS('May'!F:F,'May'!D:D,"Credit Card Payment",'May'!I:I,B5)+SUMIFS('June'!F:F,'June'!D:D,"Credit Card Payment",'June'!I:I,B5)+SUMIFS('July'!F:F,'July'!D:D,"Credit Card Payment",'July'!I:I,B5)+SUMIFS('August'!F:F,'August'!D:D,"Credit Card Payment",'August'!I:I,B5)+SUMIFS('September'!F:F,'September'!D:D,"Credit Card Payment",'September'!I:I,B5)+SUMIFS('October'!F:F,'October'!D:D,"Credit Card Payment",'October'!I:I,B5)+SUMIFS('November'!F:F,'November'!D:D,"Credit Card Payment",'November'!I:I,B5)+SUMIFS('December'!F:F,'December'!D:D,"Credit Card Payment",'December'!I:I,B5)+SUMIFS('January'!F:F,'January'!D:D,"Credit Card Payment",'January'!I:I,B5)+SUMIFS('February'!F:F,'February'!D:D,"Credit Card Payment",'February'!I:I,B5)+SUMIFS('March'!F:F,'March'!D:D,"Credit Card Payment",'March'!I:I,B5) | G5: =D5+E5-F5 | H5: =IF(C5>0,C5-G5,"")
A6: 2 | B6: =Setup!D6 | C6: =Setup!E6 | D6: =Setup!F6 | E6: =SUMIF('April'!H:H,B6,'April'!F:F)+SUMIF('May'!H:H,B6,'May'!F:F)+SUMIF('June'!H:H,B6,'June'!F:F)+SUMIF('July'!H:H,B6,'July'!F:F)+SUMIF('August'!H:H,B6,'August'!F:F)+SUMIF('September'!H:H,B6,'September'!F:F)+SUMIF('October'!H:H,B6,'October'!F:F)+SUMIF('November'!H:H,B6,'November'!F:F)+SUMIF('December'!H:H,B6,'December'!F:F)+SUMIF('January'!H:H,B6,'January'!F:F)+SUMIF('February'!H:H,B6,'February'!F:F)+SUMIF('March'!H:H,B6,'March'!F:F) | F6: =SUMIFS('April'!F:F,'April'!D:D,"Credit Card Payment",'April'!I:I,B6)+SUMIFS('May'!F:F,'May'!D:D,"Credit Card Payment",'May'!I:I,B6)+SUMIFS('June'!F:F,'June'!D:D,"Credit Card Payment",'June'!I:I,B6)+SUMIFS('July'!F:F,'July'!D:D,"Credit Card Payment",'July'!I:I,B6)+SUMIFS('August'!F:F,'August'!D:D,"Credit Card Payment",'August'!I:I,B6)+SUMIFS('September'!F:F,'September'!D:D,"Credit Card Payment",'September'!I:I,B6)+SUMIFS('October'!F:F,'October'!D:D,"Credit Card Payment",'October'!I:I,B6)+SUMIFS('November'!F:F,'November'!D:D,"Credit Card Payment",'November'!I:I,B6)+SUMIFS('December'!F:F,'December'!D:D,"Credit Card Payment",'December'!I:I,B6)+SUMIFS('January'!F:F,'January'!D:D,"Credit Card Payment",'January'!I:I,B6)+SUMIFS('February'!F:F,'February'!D:D,"Credit Card Payment",'February'!I:I,B6)+SUMIFS('March'!F:F,'March'!D:D,"Credit Card Payment",'March'!I:I,B6) | G6: =D6+E6-F6 | H6: =IF(C6>0,C6-G6,"")
A7: 3 | B7: =Setup!D7 | C7: =Setup!E7 | D7: =Setup!F7 | E7: =SUMIF('April'!H:H,B7,'April'!F:F)+SUMIF('May'!H:H,B7,'May'!F:F)+SUMIF('June'!H:H,B7,'June'!F:F)+SUMIF('July'!H:H,B7,'July'!F:F)+SUMIF('August'!H:H,B7,'August'!F:F)+SUMIF('September'!H:H,B7,'September'!F:F)+SUMIF('October'!H:H,B7,'October'!F:F)+SUMIF('November'!H:H,B7,'November'!F:F)+SUMIF('December'!H:H,B7,'December'!F:F)+SUMIF('January'!H:H,B7,'January'!F:F)+SUMIF('February'!H:H,B7,'February'!F:F)+SUMIF('March'!H:H,B7,'March'!F:F) | F7: =SUMIFS('April'!F:F,'April'!D:D,"Credit Card Payment",'April'!I:I,B7)+SUMIFS('May'!F:F,'May'!D:D,"Credit Card Payment",'May'!I:I,B7)+SUMIFS('June'!F:F,'June'!D:D,"Credit Card Payment",'June'!I:I,B7)+SUMIFS('July'!F:F,'July'!D:D,"Credit Card Payment",'July'!I:I,B7)+SUMIFS('August'!F:F,'August'!D:D,"Credit Card Payment",'August'!I:I,B7)+SUMIFS('September'!F:F,'September'!D:D,"Credit Card Payment",'September'!I:I,B7)+SUMIFS('October'!F:F,'October'!D:D,"Credit Card Payment",'October'!I:I,B7)+SUMIFS('November'!F:F,'November'!D:D,"Credit Card Payment",'November'!I:I,B7)+SUMIFS('December'!F:F,'December'!D:D,"Credit Card Payment",'December'!I:I,B7)+SUMIFS('January'!F:F,'January'!D:D,"Credit Card Payment",'January'!I:I,B7)+SUMIFS('February'!F:F,'February'!D:D,"Credit Card Payment",'February'!I:I,B7)+SUMIFS('March'!F:F,'March'!D:D,"Credit Card Payment",'March'!I:I,B7) | G7: =D7+E7-F7 | H7: =IF(C7>0,C7-G7,"")
A8: 4 | B8: =Setup!D8 | C8: =Setup!E8 | D8: =Setup!F8 | E8: =SUMIF('April'!H:H,B8,'April'!F:F)+SUMIF('May'!H:H,B8,'May'!F:F)+SUMIF('June'!H:H,B8,'June'!F:F)+SUMIF('July'!H:H,B8,'July'!F:F)+SUMIF('August'!H:H,B8,'August'!F:F)+SUMIF('September'!H:H,B8,'September'!F:F)+SUMIF('October'!H:H,B8,'October'!F:F)+SUMIF('November'!H:H,B8,'November'!F:F)+SUMIF('December'!H:H,B8,'December'!F:F)+SUMIF('January'!H:H,B8,'January'!F:F)+SUMIF('February'!H:H,B8,'February'!F:F)+SUMIF('March'!H:H,B8,'March'!F:F) | F8: =SUMIFS('April'!F:F,'April'!D:D,"Credit Card Payment",'April'!I:I,B8)+SUMIFS('May'!F:F,'May'!D:D,"Credit Card Payment",'May'!I:I,B8)+SUMIFS('June'!F:F,'June'!D:D,"Credit Card Payment",'June'!I:I,B8)+SUMIFS('July'!F:F,'July'!D:D,"Credit Card Payment",'July'!I:I,B8)+SUMIFS('August'!F:F,'August'!D:D,"Credit Card Payment",'August'!I:I,B8)+SUMIFS('September'!F:F,'September'!D:D,"Credit Card Payment",'September'!I:I,B8)+SUMIFS('October'!F:F,'October'!D:D,"Credit Card Payment",'October'!I:I,B8)+SUMIFS('November'!F:F,'November'!D:D,"Credit Card Payment",'November'!I:I,B8)+SUMIFS('December'!F:F,'December'!D:D,"Credit Card Payment",'December'!I:I,B8)+SUMIFS('January'!F:F,'January'!D:D,"Credit Card Payment",'January'!I:I,B8)+SUMIFS('February'!F:F,'February'!D:D,"Credit Card Payment",'February'!I:I,B8)+SUMIFS('March'!F:F,'March'!D:D,"Credit Card Payment",'March'!I:I,B8) | G8: =D8+E8-F8 | H8: =IF(C8>0,C8-G8,"")
A9: 5 | B9: =Setup!D9 | C9: =Setup!E9 | D9: =Setup!F9 | E9: =SUMIF('April'!H:H,B9,'April'!F:F)+SUMIF('May'!H:H,B9,'May'!F:F)+SUMIF('June'!H:H,B9,'June'!F:F)+SUMIF('July'!H:H,B9,'July'!F:F)+SUMIF('August'!H:H,B9,'August'!F:F)+SUMIF('September'!H:H,B9,'September'!F:F)+SUMIF('October'!H:H,B9,'October'!F:F)+SUMIF('November'!H:H,B9,'November'!F:F)+SUMIF('December'!H:H,B9,'December'!F:F)+SUMIF('January'!H:H,B9,'January'!F:F)+SUMIF('February'!H:H,B9,'February'!F:F)+SUMIF('March'!H:H,B9,'March'!F:F) | F9: =SUMIFS('April'!F:F,'April'!D:D,"Credit Card Payment",'April'!I:I,B9)+SUMIFS('May'!F:F,'May'!D:D,"Credit Card Payment",'May'!I:I,B9)+SUMIFS('June'!F:F,'June'!D:D,"Credit Card Payment",'June'!I:I,B9)+SUMIFS('July'!F:F,'July'!D:D,"Credit Card Payment",'July'!I:I,B9)+SUMIFS('August'!F:F,'August'!D:D,"Credit Card Payment",'August'!I:I,B9)+SUMIFS('September'!F:F,'September'!D:D,"Credit Card Payment",'September'!I:I,B9)+SUMIFS('October'!F:F,'October'!D:D,"Credit Card Payment",'October'!I:I,B9)+SUMIFS('November'!F:F,'November'!D:D,"Credit Card Payment",'November'!I:I,B9)+SUMIFS('December'!F:F,'December'!D:D,"Credit Card Payment",'December'!I:I,B9)+SUMIFS('January'!F:F,'January'!D:D,"Credit Card Payment",'January'!I:I,B9)+SUMIFS('February'!F:F,'February'!D:D,"Credit Card Payment",'February'!I:I,B9)+SUMIFS('March'!F:F,'March'!D:D,"Credit Card Payment",'March'!I:I,B9) | G9: =D9+E9-F9 | H9: =IF(C9>0,C9-G9,"")

Sheet Savings Accounts
A1: 🏦 SAVINGS ACCOUNTS — Auto-updated from monthly expense sheets
A3: # | B3: Account Name | C3: Opening Balance (₹) | D3: Total Added (₹) | E3: Total Withdrawn (₹) | F3: Current Balance (₹)
A4: 1 | B4: =Setup!A13 | C4: =Setup!B13 | D4: =SUMIFS('April'!F:F,'April'!D:D,"Added to Savings",'April'!I:I,B4)+SUMIFS('May'!F:F,'May'!D:D,"Added to Savings",'May'!I:I,B4)+SUMIFS('June'!F:F,'June'!D:D,"Added to Savings",'June'!I:I,B4)+SUMIFS('July'!F:F,'July'!D:D,"Added to Savings",'July'!I:I,B4)+SUMIFS('August'!F:F,'August'!D:D,"Added to Savings",'August'!I:I,B4)+SUMIFS('September'!F:F,'September'!D:D,"Added to Savings",'September'!I:I,B4)+SUMIFS('October'!F:F,'October'!D:D,"Added to Savings",'October'!I:I,B4)+SUMIFS('November'!F:F,'November'!D:D,"Added to Savings",'November'!I:I,B4)+SUMIFS('December'!F:F,'December'!D:D,"Added to Savings",'December'!I:I,B4)+SUMIFS('January'!F:F,'January'!D:D,"Added to Savings",'January'!I:I,B4)+SUMIFS('February'!F:F,'February'!D:D,"Added to Savings",'February'!I:I,B4)+SUMIFS('March'!F:F,'March'!D:D,"Added to Savings",'March'!I:I,B4) | E4: =SUMIFS('April'!F:F,'April'!G:G,B4)+SUMIFS('May'!F:F,'May'!G:G,B4)+SUMIFS('June'!F:F,'June'!G:G,B4)+SUMIFS('July'!F:F,'July'!G:G,B4)+SUMIFS('August'!F:F,'August'!G:G,B4)+SUMIFS('September'!F:F,'September'!G:G,B4)+SUMIFS('October'!F:F,'October'!G:G,B4)+SUMIFS('November'!F:F,'November'!G:G,B4)+SUMIFS('December'!F:F,'December'!G:G,B4)+SUMIFS('January'!F:F,'January'!G:G,B4)+SUMIFS('February'!F:F,'February'!G:G,B4)+SUMIFS('March'!F:F,'March'!G:G,B4) | F4: =C4+D4-E4
A5: 2 | B5: =Setup!A14 | C5: =Setup!B14 | D5: =SUMIFS('April'!F:F,'April'!D:D,"Added to Savings",'April'!I:I,B5)+SUMIFS('May'!F:F,'May'!D:D,"Added to Savings",'May'!I:I,B5)+SUMIFS('June'!F:F,'June'!D:D,"Added to Savings",'June'!I:I,B5)+SUMIFS('July'!F:F,'July'!D:D,"Added to Savings",'July'!I:I,B5)+SUMIFS('August'!F:F,'August'!D:D,"Added to Savings",'August'!I:I,B5)+SUMIFS('September'!F:F,'September'!D:D,"Added to Savings",'September'!I:I,B5)+SUMIFS('October'!F:F,'October'!D:D,"Added to Savings",'October'!I:I,B5)+SUMIFS('November'!F:F,'November'!D:D,"Added to Savings",'November'!I:I,B5)+SUMIFS('December'!F:F,'December'!D:D,"Added to Savings",'December'!I:I,B5)+SUMIFS('January'!F:F,'January'!D:D,"Added to Savings",'January'!I:I,B5)+SUMIFS('February'!F:F,'February'!D:D,"Added to Savings",'February'!I:I,B5)+SUMIFS('March'!F:F,'March'!D:D,"Added to Savings",'March'!I:I,B5) | E5: =SUMIFS('April'!F:F,'April'!G:G,B5)+SUMIFS('May'!F:F,'May'!G:G,B5)+SUMIFS('June'!F:F,'June'!G:G,B5)+SUMIFS('July'!F:F,'July'!G:G,B5)+SUMIFS('August'!F:F,'August'!G:G,B5)+SUMIFS('September'!F:F,'September'!G:G,B5)+SUMIFS('October'!F:F,'October'!G:G,B5)+SUMIFS('November'!F:F,'November'!G:G,B5)+SUMIFS('December'!F:F,'December'!G:G,B5)+SUMIFS('January'!F:F,'January'!G:G,B5)+SUMIFS('February'!F:F,'February'!G:G,B5)+SUMIFS('March'!F:F,'March'!G:G,B5) | F5: =C5+D5-E5
A6: 3 | B6: =Setup!A15 | C6: =Setup!B15 | D6: =SUMIFS('April'!F:F,'April'!D:D,"Added to Savings",'April'!I:I,B6)+SUMIFS('May'!F:F,'May'!D:D,"Added to Savings",'May'!I:I,B6)+SUMIFS('June'!F:F,'June'!D:D,"Added to Savings",'June'!I:I,B6)+SUMIFS('July'!F:F,'July'!D:D,"Added to Savings",'July'!I:I,B6)+SUMIFS('August'!F:F,'August'!D:D,"Added to Savings",'August'!I:I,B6)+SUMIFS('September'!F:F,'September'!D:D,"Added to Savings",'September'!I:I,B6)+SUMIFS('October'!F:F,'October'!D:D,"Added to Savings",'October'!I:I,B6)+SUMIFS('November'!F:F,'November'!D:D,"Added to Savings",'November'!I:I,B6)+SUMIFS('December'!F:F,'December'!D:D,"Added to Savings",'December'!I:I,B6)+SUMIFS('January'!F:F,'January'!D:D,"Added to Savings",'January'!I:I,B6)+SUMIFS('February'!F:F,'February'!D:D,"Added to Savings",'February'!I:I,B6)+SUMIFS('March'!F:F,'March'!D:D,"Added to Savings",'March'!I:I,B6) | E6: =SUMIFS('April'!F:F,'April'!G:G,B6)+SUMIFS('May'!F:F,'May'!G:G,B6)+SUMIFS('June'!F:F,'June'!G:G,B6)+SUMIFS('July'!F:F,'July'!G:G,B6)+SUMIFS('August'!F:F,'August'!G:G,B6)+SUMIFS('September'!F:F,'September'!G:G,B6)+SUMIFS('October'!F:F,'October'!G:G,B6)+SUMIFS('November'!F:F,'November'!G:G,B6)+SUMIFS('December'!F:F,'December'!G:G,B6)+SUMIFS('January'!F:F,'January'!G:G,B6)+SUMIFS('February'!F:F,'February'!G:G,B6)+SUMIFS('March'!F:F,'March'!G:G,B6) | F6: =C6+D6-E6
A7: 4 | B7: =Setup!A16 | C7: =Setup!B16 | D7: =SUMIFS('April'!F:F,'April'!D:D,"Added to Savings",'April'!I:I,B7)+SUMIFS('May'!F:F,'May'!D:D,"Added to Savings",'May'!I:I,B7)+SUMIFS('June'!F:F,'June'!D:D,"Added to Savings",'June'!I:I,B7)+SUMIFS('July'!F:F,'July'!D:D,"Added to Savings",'July'!I:I,B7)+SUMIFS('August'!F:F,'August'!D:D,"Added to Savings",'August'!I:I,B7)+SUMIFS('September'!F:F,'September'!D:D,"Added to Savings",'September'!I:I,B7)+SUMIFS('October'!F:F,'October'!D:D,"Added to Savings",'October'!I:I,B7)+SUMIFS('November'!F:F,'November'!D:D,"Added to Savings",'November'!I:I,B7)+SUMIFS('December'!F:F,'December'!D:D,"Added to Savings",'December'!I:I,B7)+SUMIFS('January'!F:F,'January'!D:D,"Added to Savings",'January'!I:I,B7)+SUMIFS('February'!F:F,'February'!D:D,"Added to Savings",'February'!I:I,B7)+SUMIFS('March'!F:F,'March'!D:D,"Added to Savings",'March'!I:I,B7) | E7: =SUMIFS('April'!F:F,'April'!G:G,B7)+SUMIFS('May'!F:F,'May'!G:G,B7)+SUMIFS('June'!F:F,'June'!G:G,B7)+SUMIFS('July'!F:F,'July'!G:G,B7)+SUMIFS('August'!F:F,'August'!G:G,B7)+SUMIFS('September'!F:F,'September'!G:G,B7)+SUMIFS('October'!F:F,'October'!G:G,B7)+SUMIFS('November'!F:F,'November'!G:G,B7)+SUMIFS('December'!F:F,'December'!G:G,B7)+SUMIFS('January'!F:F,'January'!G:G,B7)+SUMIFS('February'!F:F,'February'!G:G,B7)+SUMIFS('March'!F:F,'March'!G:G,B7) | F7: =C7+D7-E7
A8: 5 | B8: =Setup!A17 | C8: =Setup!B17 | D8: =SUMIFS('April'!F:F,'April'!D:D,"Added to Savings",'April'!I:I,B8)+SUMIFS('May'!F:F,'May'!D:D,"Added to Savings",'May'!I:I,B8)+SUMIFS('June'!F:F,'June'!D:D,"Added to Savings",'June'!I:I,B8)+SUMIFS('July'!F:F,'July'!D:D,"Added to Savings",'July'!I:I,B8)+SUMIFS('August'!F:F,'August'!D:D,"Added to Savings",'August'!I:I,B8)+SUMIFS('September'!F:F,'September'!D:D,"Added to Savings",'September'!I:I,B8)+SUMIFS('October'!F:F,'October'!D:D,"Added to Savings",'October'!I:I,B8)+SUMIFS('November'!F:F,'November'!D:D,"Added to Savings",'November'!I:I,B8)+SUMIFS('December'!F:F,'December'!D:D,"Added to Savings",'December'!I:I,B8)+SUMIFS('January'!F:F,'January'!D:D,"Added to Savings",'January'!I:I,B8)+SUMIFS('February'!F:F,'February'!D:D,"Added to Savings",'February'!I:I,B8)+SUMIFS('March'!F:F,'March'!D:D,"Added to Savings",'March'!I:I,B8) | E8: =SUMIFS('April'!F:F,'April'!G:G,B8)+SUMIFS('May'!F:F,'May'!G:G,B8)+SUMIFS('June'!F:F,'June'!G:G,B8)+SUMIFS('July'!F:F,'July'!G:G,B8)+SUMIFS('August'!F:F,'August'!G:G,B8)+SUMIFS('September'!F:F,'September'!G:G,B8)+SUMIFS('October'!F:F,'October'!G:G,B8)+SUMIFS('November'!F:F,'November'!G:G,B8)+SUMIFS('December'!F:F,'December'!G:G,B8)+SUMIFS('January'!F:F,'January'!G:G,B8)+SUMIFS('February'!F:F,'February'!G:G,B8)+SUMIFS('March'!F:F,'March'!G:G,B8) | F8: =C8+D8-E8

Sheet Analytics
A1: 📊 ANNUAL FINANCE DASHBOARD — Auto-updated from all 12 monthly sheets
A3: 📋 YEARLY SUMMARY
A4: 💵 Total Income | B4: =Income!E16
A5: 🧾 Total Expenses | B5: ='April'!F65+'May'!F65+'June'!F65+'July'!F65+'August'!F65+'September'!F65+'October'!F65+'November'!F65+'December'!F65+'January'!F65+'February'!F65+'March'!F65
A6: 🏠 Fixed Bills | B6: =SUMIF('April'!D5:D64,"Fixed Bills",'April'!F5:F64)+SUMIF('May'!D5:D64,"Fixed Bills",'May'!F5:F64)+SUMIF('June'!D5:D64,"Fixed Bills",'June'!F5:F64)+SUMIF('July'!D5:D64,"Fixed Bills",'July'!F5:F64)+SUMIF('August'!D5:D64,"Fixed Bills",'August'!F5:F64)+SUMIF('September'!D5:D64,"Fixed Bills",'September'!F5:F64)+SUMIF('October'!D5:D64,"Fixed Bills",'October'!F5:F64)+SUMIF('November'!D5:D64,"Fixed Bills",'November'!F5:F64)+SUMIF('December'!D5:D64,"Fixed Bills",'December'!F5:F64)+SUMIF('January'!D5:D64,"Fixed Bills",'January'!F5:F64)+SUMIF('February'!D5:D64,"Fixed Bills",'February'!F5:F64)+SUMIF('March'!D5:D64,"Fixed Bills",'March'!F5:F64)
A7: 💰 Added to Savings | B7: =SUMIF('April'!D5:D64,"Added to Savings",'April'!F5:F64)+SUMIF('May'!D5:D64,"Added to Savings",'May'!F5:F64)+SUMIF('June'!D5:D64,"Added to Savings",'June'!F5:F64)+SUMIF('July'!D5:D64,"Added to Savings",'July'!F5:F64)+SUMIF('August'!D5:D64,"Added to Savings",'August'!F5:F64)+SUMIF('September'!D5:D64,"Added to Savings",'September'!F5:F64)+SUMIF('October'!D5:D64,"Added to Savings",'October'!F5:F64)+SUMIF('November'!D5:D64,"Added to Savings",'November'!F5:F64)+SUMIF('December'!D5:D64,"Added to Savings",'December'!F5:F64)+SUMIF('January'!D5:D64,"Added to Savings",'January'!F5:F64)+SUMIF('February'!D5:D64,"Added to Savings",'February'!F5:F64)+SUMIF('March'!D5:D64,"Added to Savings",'March'!F5:F64)
A8: 📈 Investments | B8: =SUMIF('April'!D5:D64,"Investment",'April'!F5:F64)+SUMIF('May'!D5:D64,"Investment",'May'!F5:F64)+SUMIF('June'!D5:D64,"Investment",'June'!F5:F64)+SUMIF('July'!D5:D64,"Investment",'July'!F5:F64)+SUMIF('August'!D5:D64,"Investment",'August'!F5:F64)+SUMIF('September'!D5:D64,"Investment",'September'!F5:F64)+SUMIF('October'!D5:D64,"Investment",'October'!F5:F64)+SUMIF('November'!D5:D64,"Investment",'November'!F5:F64)+SUMIF('December'!D5:D64,"Investment",'December'!F5:F64)+SUMIF('January'!D5:D64,"Investment",'January'!F5:F64)+SUMIF('February'!D5:D64,"Investment",'February'!F5:F64)+SUMIF('March'!D5:D64,"Investment",'March'!F5:F64)
A9: 💳 CC Owed | B9: =SUM('Credit Cards'!F5:G9)
A10: ✅ Net Balance | B10: =B4-B5
A12: 📅 MONTH-WISE SUMMARY (Apr → Mar)
A13: Month | B13: Income (₹) | C13: Expenses (₹) | D13: Fixed Bills (₹) | E13: Savings (₹) | F13: Investment (₹) | G13: CC Paid (₹) | H13: Net (₹) | I13: Discretionary (₹) | J13: Mean Daily (₹) | K13: Median Txn (₹) | L13: Max Txn (₹) | M13: Savings Rate
A14: April | B14: =Income!E4 | C14: ='April'!F65 | D14: =SUMIF('April'!D5:D64,"Fixed Bills",'April'!F5:F64) | E14: =SUMIF('April'!D5:D64,"Added to Savings",'April'!F5:F64) | F14: =SUMIF('April'!D5:D64,"Investment",'April'!F5:F64) | G14: =SUMIF('April'!D5:D64,"Credit Card Payment",'April'!F5:F64) | H14: =B14-C14 | I14: =C14-D14-E14-F14 | J14: =I14/30 | K14: =MEDIAN(IF(('April'!D5:D64<>"Fixed Bills")*('April'!D5:D64<>"Investment")*('April'!D5:D64<>"Added to Savings")*('April'!F5:F64>0),'April'!F5:F64)) | L14: =MAX(IF(('April'!D5:D64<>"Fixed Bills")*('April'!D5:D64<>"Investment")*('April'!D5:D64<>"Added to Savings")*('April'!F5:F64>0),'April'!F5:F64)) | M14: =IF(B14>0,(B14-C14)/B14,0)
A15: May | B15: =Income!E5 | C15: ='May'!F65 | D15: =SUMIF('May'!D5:D64,"Fixed Bills",'May'!F5:F64) | E15: =SUMIF('May'!D5:D64,"Added to Savings",'May'!F5:F64) | F15: =SUMIF('May'!D5:D64,"Investment",'May'!F5:F64) | G15: =SUMIF('May'!D5:D64,"Credit Card Payment",'May'!F5:F64) | H15: =B15-C15 | I15: =C15-D15-E15-F15 | J15: =I15/31 | K15: =MEDIAN(IF(('May'!D5:D64<>"Fixed Bills")*('May'!D5:D64<>"Investment")*('May'!D5:D64<>"Added to Savings")*('May'!F5:F64>0),'May'!F5:F64)) | L15: =MAX(IF(('May'!D5:D64<>"Fixed Bills")*('May'!D5:D64<>"Investment")*('May'!D5:D64<>"Added to Savings")*('May'!F5:F64>0),'May'!F5:F64)) | M15: =IF(B15>0,(B15-C15)/B15,0)
A16: June | B16: =Income!E6 | C16: ='June'!F65 | D16: =SUMIF('June'!D5:D64,"Fixed Bills",'June'!F5:F64) | E16: =SUMIF('June'!D5:D64,"Added to Savings",'June'!F5:F64) | F16: =SUMIF('June'!D5:D64,"Investment",'June'!F5:F64) | G16: =SUMIF('June'!D5:D64,"Credit Card Payment",'June'!F5:F64) | H16: =B16-C16 | I16: =C16-D16-E16-F16 | J16: =I16/30 | K16: =MEDIAN(IF(('June'!D5:D64<>"Fixed Bills")*('June'!D5:D64<>"Investment")*('June'!D5:D64<>"Added to Savings")*('June'!F5:F64>0),'June'!F5:F64)) | L16: =MAX(IF(('June'!D5:D64<>"Fixed Bills")*('June'!D5:D64<>"Investment")*('June'!D5:D64<>"Added to Savings")*('June'!F5:F64>0),'June'!F5:F64)) | M16: =IF(B16>0,(B16-C16)/B16,0)
A17: July | B17: =Income!E7 | C17: ='July'!F65 | D17: =SUMIF('July'!D5:D64,"Fixed Bills",'July'!F5:F64) | E17: =SUMIF('July'!D5:D64,"Added to Savings",'July'!F5:F64) | F17: =SUMIF('July'!D5:D64,"Investment",'July'!F5:F64) | G17: =SUMIF('July'!D5:D64,"Credit Card Payment",'July'!F5:F64) | H17: =B17-C17 | I17: =C17-D17-E17-F17 | J17: =I17/31 | K17: =MEDIAN(IF(('July'!D5:D64<>"Fixed Bills")*('July'!D5:D64<>"Investment")*('July'!D5:D64<>"Added to Savings")*('July'!F5:F64>0),'July'!F5:F64)) | L17: =MAX(IF(('July'!D5:D64<>"Fixed Bills")*('July'!D5:D64<>"Investment")*('July'!D5:D64<>"Added to Savings")*('July'!F5:F64>0),'July'!F5:F64)) | M17: =IF(B17>0,(B17-C17)/B17,0)
A18: August | B18: =Income!E8 | C18: ='August'!F65 | D18: =SUMIF('August'!D5:D64,"Fixed Bills",'August'!F5:F64) | E18: =SUMIF('August'!D5:D64,"Added to Savings",'August'!F5:F64) | F18: =SUMIF('August'!D5:D64,"Investment",'August'!F5:F64) | G18: =SUMIF('August'!D5:D64,"Credit Card Payment",'August'!F5:F64) | H18: =B18-C18 | I18: =C18-D18-E18-F18 | J18: =I18/31 | K18: =MEDIAN(IF(('August'!D5:D64<>"Fixed Bills")*('August'!D5:D64<>"Investment")*('August'!D5:D64<>"Added to Savings")*('August'!F5:F64>0),'August'!F5:F64)) | L18: =MAX(IF(('August'!D5:D64<>"Fixed Bills")*('August'!D5:D64<>"Investment")*('August'!D5:D64<>"Added to Savings")*('August'!F5:F64>0),'August'!F5:F64)) | M18: =IF(B18>0,(B18-C18)/B18,0)
A19: September | B19: =Income!E9 | C19: ='September'!F65 | D19: =SUMIF('September'!D5:D64,"Fixed Bills",'September'!F5:F64) | E19: =SUMIF('September'!D5:D64,"Added to Savings",'September'!F5:F64) | F19: =SUMIF('September'!D5:D64,"Investment",'September'!F5:F64) | G19: =SUMIF('September'!D5:D64,"Credit Card Payment",'September'!F5:F64) | H19: =B19-C19 | I19: =C19-D19-E19-F19 | J19: =I19/30 | K19: =MEDIAN(IF(('September'!D5:D64<>"Fixed Bills")*('September'!D5:D64<>"Investment")*('September'!D5:D64<>"Added to Savings")*('September'!F5:F64>0),'September'!F5:F64)) | L19: =MAX(IF(('September'!D5:D64<>"Fixed Bills")*('September'!D5:D64<>"Investment")*('September'!D5:D64<>"Added to Savings")*('September'!F5:F64>0),'September'!F5:F64)) | M19: =IF(B19>0,(B19-C19)/B19,0)
A20: October | B20: =Income!E10 | C20: ='October'!F65 | D20: =SUMIF('October'!D5:D64,"Fixed Bills",'October'!F5:F64) | E20: =SUMIF('October'!D5:D64,"Added to Savings",'October'!F5:F64) | F20: =SUMIF('October'!D5:D64,"Investment",'October'!F5:F64) | G20: =SUMIF('October'!D5:D64,"Credit Card Payment",'October'!F5:F64) | H20: =B20-C20 | I20: =C20-D20-E20-F20 | J20: =I20/31 | K20: =MEDIAN(IF(('October'!D5:D64<>"Fixed Bills")*('October'!D5:D64<>"Investment")*('October'!D5:D64<>"Added to Savings")*('October'!F5:F64>0),'October'!F5:F64)) | L20: =MAX(IF(('October'!D5:D64<>"Fixed Bills")*('October'!D5:D64<>"Investment")*('October'!D5:D64<>"Added to Savings")*('October'!F5:F64>0),'October'!F5:F64)) | M20: =IF(B20>0,(B20-C20)/B20,0)
A21: November | B21: =Income!E11 | C21: ='November'!F65 | D21: =SUMIF('November'!D5:D64,"Fixed Bills",'November'!F5:F64) | E21: =SUMIF('November'!D5:D64,"Added to Savings",'November'!F5:F64) | F21: =SUMIF('November'!D5:D64,"Investment",'November'!F5:F64) | G21: =SUMIF('November'!D5:D64,"Credit Card Payment",'November'!F5:F64) | H21: =B21-C21 | I21: =C21-D21-E21-F21 | J21: =I21/30 | K21: =MEDIAN(IF(('November'!D5:D64<>"Fixed Bills")*('November'!D5:D64<>"Investment")*('November'!D5:D64<>"Added to Savings")*('November'!F5:F64>0),'November'!F5:F64)) | L21: =MAX(IF(('November'!D5:D64<>"Fixed Bills")*('November'!D5:D64<>"Investment")*('November'!D5:D64<>"Added to Savings")*('November'!F5:F64>0),'November'!F5:F64)) | M21: =IF(B21>0,(B21-C21)/B21,0)
A22: December | B22: =Income!E12 | C22: ='December'!F65 | D22: =SUMIF('December'!D5:D64,"Fixed Bills",'December'!F5:F64) | E22: =SUMIF('December'!D5:D64,"Added to Savings",'December'!F5:F64) | F22: =SUMIF('December'!D5:D64,"Investment",'December'!F5:F64) | G22: =SUMIF('December'!D5:D64,"Credit Card Payment",'December'!F5:F64) | H22: =B22-C22 | I22: =C22-D22-E22-F22 | J22: =I22/31 | K22: =MEDIAN(IF(('December'!D5:D64<>"Fixed Bills")*('December'!D5:D64<>"Investment")*('December'!D5:D64<>"Added to Savings")*('December'!F5:F64>0),'December'!F5:F64)) | L22: =MAX(IF(('December'!D5:D64<>"Fixed Bills")*('December'!D5:D64<>"Investment")*('December'!D5:D64<>"Added to Savings")*('December'!F5:F64>0),'December'!F5:F64)) | M22: =IF(B22>0,(B22-C22)/B22,0)
A23: January | B23: =Income!E13 | C23: ='January'!F65 | D23: =SUMIF('January'!D5:D64,"Fixed Bills",'January'!F5:F64) | E23: =SUMIF('January'!D5:D64,"Added to Savings",'January'!F5:F64) | F23: =SUMIF('January'!D5:D64,"Investment",'January'!F5:F64) | G23: =SUMIF('January'!D5:D64,"Credit Card Payment",'January'!F5:F64) | H23: =B23-C23 | I23: =C23-D23-E23-F23 | J23: =I23/31 | K23: =MEDIAN(IF(('January'!D5:D64<>"Fixed Bills")*('January'!D5:D64<>"Investment")*('January'!D5:D64<>"Added to Savings")*('January'!F5:F64>0),'January'!F5:F64)) | L23: =MAX(IF(('January'!D5:D64<>"Fixed Bills")*('January'!D5:D64<>"Investment")*('January'!D5:D64<>"Added to Savings")*('January'!F5:F64>0),'January'!F5:F64)) | M23: =IF(B23>0,(B23-C23)/B23,0)
A24: February | B24: =Income!E14 | C24: ='February'!F65 | D24: =SUMIF('February'!D5:D64,"Fixed Bills",'February'!F5:F64) | E24: =SUMIF('February'!D5:D64,"Added to Savings",'February'!F5:F64) | F24: =SUMIF('February'!D5:D64,"Investment",'February'!F5:F64) | G24: =SUMIF('February'!D5:D64,"Credit Card Payment",'February'!F5:F64) | H24: =B24-C24 | I24: =C24-D24-E24-F24 | J24: =I24/28 | K24: =MEDIAN(IF(('February'!D5:D64<>"Fixed Bills")*('February'!D5:D64<>"Investment")*('February'!D5:D64<>"Added to Savings")*('February'!F5:F64>0),'February'!F5:F64)) | L24: =MAX(IF(('February'!D5:D64<>"Fixed Bills")*('February'!D5:D64<>"Investment")*('February'!D5:D64<>"Added to Savings")*('February'!F5:F64>0),'February'!F5:F64)) | M24: =IF(B24>0,(B24-C24)/B24,0)
A25: March | B25: =Income!E15 | C25: ='March'!F65 | D25: =SUMIF('March'!D5:D64,"Fixed Bills",'March'!F5:F64) | E25: =SUMIF('March'!D5:D64,"Added to Savings",'March'!F5:F64) | F25: =SUMIF('March'!D5:D64,"Investment",'March'!F5:F64) | G25: =SUMIF('March'!D5:D64,"Credit Card Payment",'March'!F5:F64) | H25: =B25-C25 | I25: =C25-D25-E25-F25 | J25: =I25/31 | K25: =MEDIAN(IF(('March'!D5:D64<>"Fixed Bills")*('March'!D5:D64<>"Investment")*('March'!D5:D64<>"Added to Savings")*('March'!F5:F64>0),'March'!F5:F64)) | L25: =MAX(IF(('March'!D5:D64<>"Fixed Bills")*('March'!D5:D64<>"Investment")*('March'!D5:D64<>"Added to Savings")*('March'!F5:F64>0),'March'!F5:F64)) | M25: =IF(B25>0,(B25-C25)/B25,0)
A26: ANNUAL | B26: =SUM(B14:B25) | C26: =SUM(C14:C25) | D26: =SUM(D14:D25) | E26: =SUM(E14:E25) | F26: =SUM(F14:F25) | G26: =SUM(G14:G25) | H26: =SUM(H14:H25) | I26: =SUM(I14:I25) | J26: =AVERAGE(J14:J25) | K26: =AVERAGE(K14:K25) | L26: =MAX(L14:L25) | M26: =AVERAGE(M14:M25)
A28: 🗂️ EXPENSE BREAKDOWN BY CATEGORY
A29: Category | B29: Spent (₹) | C29: % of Total
A30: Fixed Bills | B30: =SUMIF('April'!D5:D64,A30,'April'!F5:F64)+SUMIF('May'!D5:D64,A30,'May'!F5:F64)+SUMIF('June'!D5:D64,A30,'June'!F5:F64)+SUMIF('July'!D5:D64,A30,'July'!F5:F64)+SUMIF('August'!D5:D64,A30,'August'!F5:F64)+SUMIF('September'!D5:D64,A30,'September'!F5:F64)+SUMIF('October'!D5:D64,A30,'October'!F5:F64)+SUMIF('November'!D5:D64,A30,'November'!F5:F64)+SUMIF('December'!D5:D64,A30,'December'!F5:F64)+SUMIF('January'!D5:D64,A30,'January'!F5:F64)+SUMIF('February'!D5:D64,A30,'February'!F5:F64)+SUMIF('March'!D5:D64,A30,'March'!F5:F64) | C30: =IF(B5>0,B30/B5,0)
A31: Food & Dining | B31: =SUMIF('April'!D5:D64,A31,'April'!F5:F64)+SUMIF('May'!D5:D64,A31,'May'!F5:F64)+SUMIF('June'!D5:D64,A31,'June'!F5:F64)+SUMIF('July'!D5:D64,A31,'July'!F5:F64)+SUMIF('August'!D5:D64,A31,'August'!F5:F64)+SUMIF('September'!D5:D64,A31,'September'!F5:F64)+SUMIF('October'!D5:D64,A31,'October'!F5:F64)+SUMIF('November'!D5:D64,A31,'November'!F5:F64)+SUMIF('December'!D5:D64,A31,'December'!F5:F64)+SUMIF('January'!D5:D64,A31,'January'!F5:F64)+SUMIF('February'!D5:D64,A31,'February'!F5:F64)+SUMIF('March'!D5:D64,A31,'March'!F5:F64) | C31: =IF(B5>0,B31/B5,0)
A32: Transport & Fuel | B32: =SUMIF('April'!D5:D64,A32,'April'!F5:F64)+SUMIF('May'!D5:D64,A32,'May'!F5:F64)+SUMIF('June'!D5:D64,A32,'June'!F5:F64)+SUMIF('July'!D5:D64,A32,'July'!F5:F64)+SUMIF('August'!D5:D64,A32,'August'!F5:F64)+SUMIF('September'!D5:D64,A32,'September'!F5:F64)+SUMIF('October'!D5:D64,A32,'October'!F5:F64)+SUMIF('November'!D5:D64,A32,'November'!F5:F64)+SUMIF('December'!D5:D64,A32,'December'!F5:F64)+SUMIF('January'!D5:D64,A32,'January'!F5:F64)+SUMIF('February'!D5:D64,A32,'February'!F5:F64)+SUMIF('March'!D5:D64,A32,'March'!F5:F64) | C32: =IF(B5>0,B32/B5,0)
A33: Shopping & Clothing | B33: =SUMIF('April'!D5:D64,A33,'April'!F5:F64)+SUMIF('May'!D5:D64,A33,'May'!F5:F64)+SUMIF('June'!D5:D64,A33,'June'!F5:F64)+SUMIF('July'!D5:D64,A33,'July'!F5:F64)+SUMIF('August'!D5:D64,A33,'August'!F5:F64)+SUMIF('September'!D5:D64,A33,'September'!F5:F64)+SUMIF('October'!D5:D64,A33,'October'!F5:F64)+SUMIF('November'!D5:D64,A33,'November'!F5:F64)+SUMIF('December'!D5:D64,A33,'December'!F5:F64)+SUMIF('January'!D5:D64,A33,'January'!F5:F64)+SUMIF('February'!D5:D64,A33,'February'!F5:F64)+SUMIF('March'!D5:D64,A33,'March'!F5:F64) | C33: =IF(B5>0,B33/B5,0)
A34: Entertainment & OTT | B34: =SUMIF('April'!D5:D64,A34,'April'!F5:F64)+SUMIF('May'!D5:D64,A34,'May'!F5:F64)+SUMIF('June'!D5:D64,A34,'June'!F5:F64)+SUMIF('July'!D5:D64,A34,'July'!F5:F64)+SUMIF('August'!D5:D64,A34,'August'!F5:F64)+SUMIF('September'!D5:D64,A34,'September'!F5:F64)+SUMIF('October'!D5:D64,A34,'October'!F5:F64)+SUMIF('November'!D5:D64,A34,'November'!F5:F64)+SUMIF('December'!D5:D64,A34,'December'!F5:F64)+SUMIF('January'!D5:D64,A34,'January'!F5:F64)+SUMIF('February'!D5:D64,A34,'February'!F5:F64)+SUMIF('March'!D5:D64,A34,'March'!F5:F64) | C34: =IF(B5>0,B34/B5,0)
A35: Groceries | B35: =SUMIF('April'!D5:D64,A35,'April'!F5:F64)+SUMIF('May'!D5:D64,A35,'May'!F5:F64)+SUMIF('June'!D5:D64,A35,'June'!F5:F64)+SUMIF('July'!D5:D64,A35,'July'!F5:F64)+SUMIF('August'!D5:D64,A35,'August'!F5:F64)+SUMIF('September'!D5:D64,A35,'September'!F5:F64)+SUMIF('October'!D5:D64,A35,'October'!F5:F64)+SUMIF('November'!D5:D64,A35,'November'!F5:F64)+SUMIF('December'!D5:D64,A35,'December'!F5:F64)+SUMIF('January'!D5:D64,A35,'January'!F5:F64)+SUMIF('February'!D5:D64,A35,'February'!F5:F64)+SUMIF('March'!D5:D64,A35,'March'!F5:F64) | C35: =IF(B5>0,B35/B5,0)
A36: Investment | B36: =SUMIF('April'!D5:D64,A36,'April'!F5:F64)+SUMIF('May'!D5:D64,A36,'May'!F5:F64)+SUMIF('June'!D5:D64,A36,'June'!F5:F64)+SUMIF('July'!D5:D64,A36,'July'!F5:F64)+SUMIF('August'!D5:D64,A36,'August'!F5:F64)+SUMIF('September'!D5:D64,A36,'September'!F5:F64)+SUMIF('October'!D5:D64,A36,'October'!F5:F64)+SUMIF('November'!D5:D64,A36,'November'!F5:F64)+SUMIF('December'!D5:D64,A36,'December'!F5:F64)+SUMIF('January'!D5:D64,A36,'January'!F5:F64)+SUMIF('February'!D5:D64,A36,'February'!F5:F64)+SUMIF('March'!D5:D64,A36,'March'!F5:F64) | C36: =IF(B5>0,B36/B5,0)
A37: Added to Savings | B37: =SUMIF('April'!D5:D64,A37,'April'!F5:F64)+SUMIF('May'!D5:D64,A37,'May'!F5:F64)+SUMIF('June'!D5:D64,A37,'June'!F5:F64)+SUMIF('July'!D5:D64,A37,'July'!F5:F64)+SUMIF('August'!D5:D64,A37,'August'!F5:F64)+SUMIF('September'!D5:D64,A37,'September'!F5:F64)+SUMIF('October'!D5:D64,A37,'October'!F5:F64)+SUMIF('November'!D5:D64,A37,'November'!F5:F64)+SUMIF('December'!D5:D64,A37,'December'!F5:F64)+SUMIF('January'!D5:D64,A37,'January'!F5:F64)+SUMIF('February'!D5:D64,A37,'February'!F5:F64)+SUMIF('March'!D5:D64,A37,'March'!F5:F64) | C37: =IF(B5>0,B37/B5,0)
A38: Credit Card Payment | B38: =SUMIF('April'!D5:D64,A38,'April'!F5:F64)+SUMIF('May'!D5:D64,A38,'May'!F5:F64)+SUMIF('June'!D5:D64,A38,'June'!F5:F64)+SUMIF('July'!D5:D64,A38,'July'!F5:F64)+SUMIF('August'!D5:D64,A38,'August'!F5:F64)+SUMIF('September'!D5:D64,A38,'September'!F5:F64)+SUMIF('October'!D5:D64,A38,'October'!F5:F64)+SUMIF('November'!D5:D64,A38,'November'!F5:F64)+SUMIF('December'!D5:D64,A38,'December'!F5:F64)+SUMIF('January'!D5:D64,A38,'January'!F5:F64)+SUMIF('February'!D5:D64,A38,'February'!F5:F64)+SUMIF('March'!D5:D64,A38,'March'!F5:F64) | C38: =IF(B5>0,B38/B5,0)
A39: Miscellaneous | B39: =SUMIF('April'!D5:D64,A39,'April'!F5:F64)+SUMIF('May'!D5:D64,A39,'May'!F5:F64)+SUMIF('June'!D5:D64,A39,'June'!F5:F64)+SUMIF('July'!D5:D64,A39,'July'!F5:F64)+SUMIF('August'!D5:D64,A39,'August'!F5:F64)+SUMIF('September'!D5:D64,A39,'September'!F5:F64)+SUMIF('October'!D5:D64,A39,'October'!F5:F64)+SUMIF('November'!D5:D64,A39,'November'!F5:F64)+SUMIF('December'!D5:D64,A39,'December'!F5:F64)+SUMIF('January'!D5:D64,A39,'January'!F5:F64)+SUMIF('February'!D5:D64,A39,'February'!F5:F64)+SUMIF('March'!D5:D64,A39,'March'!F5:F64) | C39: =IF(B5>0,B39/B5,0)
A41: 🔍 DISCRETIONARY INSIGHTS (excl. Fixed Bills / Investment / Savings)
A42: Metric | B42: Value
A43: Avg Monthly Discretionary | B43: =I26/12
A44: Avg Daily Discretionary (year) | B44: =I26/365
A45: Avg of Monthly Medians | B45: =AVERAGE(K14:K25)
A46: Highest Single Txn (full year) | B46: =MAX(L14:L25)
A47: Best Month — Savings Rate | B47: =INDEX(A14:A25,MATCH(MAX(M14:M25),M14:M25,0))
A48: Worst Month — Savings Rate | B48: =INDEX(A14:A25,MATCH(MIN(M14:M25),M14:M25,0))
A49: Best Savings Rate | B49: =MAX(M14:M25)
A50: Worst Savings Rate | B50: =MIN(M14:M25)
A51: Avg Savings Rate (year) | B51: =AVERAGE(M14:M25)

Sheet _Lists
A1: Fixed Bills | B1: Salary | C1: Rent / Home Loan EMI | D1: Restaurants | E1: Fuel | F1: Clothing | G1: Movies / Events | H1: Vegetables & Fruits | I1: SIP / Mutual Funds | K1: Full Payment | L1: Medical | N1: April | O1: Rent / Home Loan EMI | P1: =Setup!A13 | Q1: Salary
A2: Food & Dining | B2: Savings Account | C2: Electricity | D2: Swiggy / Zomato | E2: Auto / Cab | F2: Electronics | G2: OTT Subscriptions | H2: Dairy | I2: Fixed Deposit | K2: Minimum Due | L2: Education | N2: May | O2: Electricity | P2: =Setup!A14 | Q2: Cash
A3: Transport & Fuel | B3: Cash | C3: Internet / WiFi | D3: Cafes | E3: Metro / Bus | F3: Home & Decor | G3: Gaming | H3: Supermarket | I3: Gold / Others | K3: Partial Payment | L3: Gifts | N3: June | O3: Internet / WiFi | P3: =Setup!A15 | Q3: UPI
A4: Shopping & Clothing | B4: UPI | C4: Mobile Recharge | D4: Street Food | E4: Parking | F4: Online Shopping | G4: Other | H4: Kirana Store | I4: Stocks | L4: Charity | N4: July | O4: Mobile Recharge | P4: =Setup!A16 | Q4: =Setup!A13
A5: Entertainment & OTT | B5: Credit Card | C5: OTT Subscriptions | D5: Other | E5: Vehicle Maintenance | F5: Other | H5: Other | I5: PPF / NPS | L5: Other | N5: August | O5: OTT Subscriptions | P5: =Setup!A17 | Q5: =Setup!A14
A6: Groceries | C6: Insurance Premium | E6: Other | I6: Other Investment | N6: September | O6: Insurance Premium | Q6: =Setup!A15
A7: Investment | C7: Gym / Fitness | N7: October | O7: Gym / Fitness | Q7: =Setup!A16
A8: Added to Savings | C8: Other Bill | N8: November | O8: Other Bill | Q8: =Setup!A17
A9: Credit Card Payment | N9: December | O9: Restaurants
A10: Miscellaneous | N10: January | O10: Swiggy / Zomato
N11: February | O11: Cafes
N12: March | O12: Street Food
O13: Other
O14: Fuel
O15: Auto / Cab
O16: Metro / Bus
O17: Parking
O18: Vehicle Maintenance
O19: Clothing
O20: Electronics
O21: Home & Decor
O22: Online Shopping
O23: Movies / Events
O24: Gaming
... O41: Charity
